Workbook

Sheet Cover
B2: Job Cost & WIP Report
B3: Boreal Ridge Construction Ltd. (fictional company)
B4: Period ending September 30, 2026
B6: SAMPLE DATA NOTICE | C6: Representative rebuild of ERP cost reporting delivered for construction clients. The company, jobs, vendors and all figures are synthetic; client data is confidential.
B8: Report date | C8: =DATE(2026,9,30) -> 46295
B10: SHEETS
B11: WIP Schedule | C11: Portfolio view: contract, cost to date, forecast cost, % complete, earned revenue, over/(under) billing, projected margin and fade, CPI and backlog for every job.
B12: Job Detail | C12: Pick a job number in the yellow cell to see its cost-code report, forecast overruns and labour productivity.
B13: Cost Report | C13: Cost-code level calculation that feeds both reports (one row per job / cost code budget line).
B14: Monthly Cost | C14: Monthly and cumulative cost by job from the job cost ledger, with a portfolio cost curve.
B15: Data_* tabs | C15: Raw ERP exports: job master, cost codes, budgets, PM progress, commitments, job cost detail, billings. Paste a new month's export over these tables to refresh.
B17: METHOD
B18: Earned value | C18: Revised budget x PM-reported physical % complete for the cost code.
B19: CPI | C19: Earned value / actual cost. Below 1.00 means the work is costing more than budgeted.
B20: Forecast cost (EAC) | C20: Subcontract & material lines with a commitment: the greater of committed value and cost to date. Other lines in progress: cost to date + remaining budget / CPI. Lines not started: revised budget.
B21: % complete (revenue) | C21: Cost-to-cost method: cost to date / forecast cost.
B22: Earned revenue | C22: Revised contract x % complete.
B23: Over/(under) billing | C23: Billed to date - earned revenue. Positive = billings in excess of revenue (liability); negative = revenue in excess of billings (asset).
B24: Margin fade | C24: Projected margin % - bid margin %. Negative = profit eroding since bid.
B26: COLOUR KEY
B27: Blue on yellow | C27: Input you can change (the job selector on Job Detail).
B28: Black | C28: Formula.

Sheet WIP Schedule
A1: Work-in-Progress Schedule
A2: Boreal Ridge Construction Ltd. (fictional) · Period ending September 30, 2026 · Percentage-of-completion, cost-to-cost method
A4: Job No | B4: Job Name | C4: PM | D4: Status | E4: Revised Contract | F4: Revised Budget | G4: Cost to Date | H4: Committed | I4: Forecast Cost (EAC) | J4: Cost to Complete | K4: % Complete | L4: Earned Revenue | M4: Billed to Date | N4: Over/(Under) Billing | O4: Projected Gross Profit | P4: Projected Margin | Q4: Bid Margin | R4: Margin Fade | S4: CPI | T4: Backlog
A5: 23-098 | B5: =INDEX(Data_Jobs!$B:$B,MATCH($A5,Data_Jobs!$A:$A,0)) -> Transit Bus Garage Upgrade | C5: =INDEX(Data_Jobs!$E:$E,MATCH($A5,Data_Jobs!$A:$A,0)) -> R. Singh | D5: =INDEX(Data_Jobs!$L:$L,MATCH($A5,Data_Jobs!$A:$A,0)) -> Substantially complete | E5: =INDEX(Data_Jobs!$K:$K,MATCH($A5,Data_Jobs!$A:$A,0)) -> 15462000 | F5: =SUMIFS('Cost Report'!$G$5:$G$180,'Cost Report'!$A$5:$A$180,$A5) -> 13811100 | G5: =SUMIFS('Cost Report'!$H$5:$H$180,'Cost Report'!$A$5:$A$180,$A5) -> 14275865 | H5: =SUMIFS('Cost Report'!$I$5:$I$180,'Cost Report'!$A$5:$A$180,$A5) -> 11358200 | I5: =SUMIFS('Cost Report'!$M$5:$M$180,'Cost Report'!$A$5:$A$180,$A5) -> 14408910 | J5: =I5-G5 -> 133044.48 | K5: =IF(I5>0,G5/I5,0) -> 0.99076651 | L5: =E5*K5 -> 15319232 | M5: =SUMIFS(Data_Billings!$E:$E,Data_Billings!$D:$D,$A5) -> 15319587 | N5: =M5-L5 -> 355.62911 | O5: =E5-I5 -> 1053090.1 | P5: =IF(E5>0,O5/E5,0) -> 0.068108274 | Q5: =INDEX(Data_Jobs!$H:$H,MATCH($A5,Data_Jobs!$A:$A,0)) -> 0.105 | R5: =P5-Q5 -> -0.036891726 | S5: =IF(G5>0,SUMIFS('Cost Report'!$K$5:$K$180,'Cost Report'!$A$5:$A$180,$A5)/G5,"") -> 0.96596512 | T5: =E5-L5 -> 142768.17
A6: 24-101 | B6: =INDEX(Data_Jobs!$B:$B,MATCH($A6,Data_Jobs!$A:$A,0)) -> Leduc Distribution Warehouse | C6: =INDEX(Data_Jobs!$E:$E,MATCH($A6,Data_Jobs!$A:$A,0)) -> M. Okafor | D6: =INDEX(Data_Jobs!$L:$L,MATCH($A6,Data_Jobs!$A:$A,0)) -> In progress | E6: =INDEX(Data_Jobs!$K:$K,MATCH($A6,Data_Jobs!$A:$A,0)) -> 22245000 | F6: =SUMIFS('Cost Report'!$G$5:$G$180,'Cost Report'!$A$5:$A$180,$A6) -> 20085200 | G6: =SUMIFS('Cost Report'!$H$5:$H$180,'Cost Report'!$A$5:$A$180,$A6) -> 19031041 | H6: =SUMIFS('Cost Report'!$I$5:$I$180,'Cost Report'!$A$5:$A$180,$A6) -> 15186100 | I6: =SUMIFS('Cost Report'!$M$5:$M$180,'Cost Report'!$A$5:$A$180,$A6) -> 19799870 | J6: =I6-G6 -> 768828.93 | K6: =IF(I6>0,G6/I6,0) -> 0.96117 | L6: =E6*K6 -> 21381227 | M6: =SUMIFS(Data_Billings!$E:$E,Data_Billings!$D:$D,$A6) -> 22246320 | N6: =M6-L6 -> 865093.75 | O6: =E6-I6 -> 2445129.6 | P6: =IF(E6>0,O6/E6,0) -> 0.10991817 | Q6: =INDEX(Data_Jobs!$H:$H,MATCH($A6,Data_Jobs!$A:$A,0)) -> 0.095 | R6: =P6-Q6 -> 0.014918166 | S6: =IF(G6>0,SUMIFS('Cost Report'!$K$5:$K$180,'Cost Report'!$A$5:$A$180,$A6)/G6,"") -> 1.0270026 | T6: =E6-L6 -> 863773.3
A7: 24-104 | B7: =INDEX(Data_Jobs!$B:$B,MATCH($A7,Data_Jobs!$A:$A,0)) -> School Modernization - Phase 2 | C7: =INDEX(Data_Jobs!$E:$E,MATCH($A7,Data_Jobs!$A:$A,0)) -> J. Tremblay | D7: =INDEX(Data_Jobs!$L:$L,MATCH($A7,Data_Jobs!$A:$A,0)) -> In progress | E7: =INDEX(Data_Jobs!$K:$K,MATCH($A7,Data_Jobs!$A:$A,0)) -> 16538000 | F7: =SUMIFS('Cost Report'!$G$5:$G$180,'Cost Report'!$A$5:$A$180,$A7) -> 14705200 | G7: =SUMIFS('Cost Report'!$H$5:$H$180,'Cost Report'!$A$5:$A$180,$A7) -> 13766951 | H7: =SUMIFS('Cost Report'!$I$5:$I$180,'Cost Report'!$A$5:$A$180,$A7) -> 11693400 | I7: =SUMIFS('Cost Report'!$M$5:$M$180,'Cost Report'!$A$5:$A$180,$A7) -> 15394483 | J7: =I7-G7 -> 1627531.9 | K7: =IF(I7>0,G7/I7,0) -> 0.89427824 | L7: =E7*K7 -> 14789573 | M7: =SUMIFS(Data_Billings!$E:$E,Data_Billings!$D:$D,$A7) -> 14186235 | N7: =M7-L7 -> -603338.01 | O7: =E7-I7 -> 1143516.7 | P7: =IF(E7>0,O7/E7,0) -> 0.069144798 | Q7: =INDEX(Data_Jobs!$H:$H,MATCH($A7,Data_Jobs!$A:$A,0)) -> 0.11 | R7: =P7-Q7 -> -0.040855202 | S7: =IF(G7>0,SUMIFS('Cost Report'!$K$5:$K$180,'Cost Report'!$A$5:$A$180,$A7)/G7,"") -> 0.9717383 | T7: =E7-L7 -> 1748426.5
A8: 24-107 | B8: =INDEX(Data_Jobs!$B:$B,MATCH($A8,Data_Jobs!$A:$A,0)) -> Fabrication Shop Expansion | C8: =INDEX(Data_Jobs!$E:$E,MATCH($A8,Data_Jobs!$A:$A,0)) -> M. Okafor | D8: =INDEX(Data_Jobs!$L:$L,MATCH($A8,Data_Jobs!$A:$A,0)) -> In progress | E8: =INDEX(Data_Jobs!$K:$K,MATCH($A8,Data_Jobs!$A:$A,0)) -> 10160000 | F8: =SUMIFS('Cost Report'!$G$5:$G$180,'Cost Report'!$A$5:$A$180,$A8) -> 8928400 | G8: =SUMIFS('Cost Report'!$H$5:$H$180,'Cost Report'!$A$5:$A$180,$A8) -> 8639590.5 | H8: =SUMIFS('Cost Report'!$I$5:$I$180,'Cost Report'!$A$5:$A$180,$A8) -> 6548600 | I8: =SUMIFS('Cost Report'!$M$5:$M$180,'Cost Report'!$A$5:$A$180,$A8) -> 8812195.1 | J8: =I8-G8 -> 172604.6 | K8: =IF(I8>0,G8/I8,0) -> 0.98041298 | L8: =E8*K8 -> 9960995.9 | M8: =SUMIFS(Data_Billings!$E:$E,Data_Billings!$D:$D,$A8) -> 10159341 | N8: =M8-L8 -> 198345.04 | O8: =E8-I8 -> 1347804.9 | P8: =IF(E8>0,O8/E8,0) -> 0.13265796 | Q8: =INDEX(Data_Jobs!$H:$H,MATCH($A8,Data_Jobs!$A:$A,0)) -> 0.12 | R8: =P8-Q8 -> 0.012657964 | S8: =IF(G8>0,SUMIFS('Cost Report'!$K$5:$K$180,'Cost Report'!$A$5:$A$180,$A8)/G8,"") -> 1.0293258 | T8: =E8-L8 -> 199004.07
A9: 25-110 | B9: =INDEX(Data_Jobs!$B:$B,MATCH($A9,Data_Jobs!$A:$A,0)) -> Medical Office Building | C9: =INDEX(Data_Jobs!$E:$E,MATCH($A9,Data_Jobs!$A:$A,0)) -> S. Chen | D9: =INDEX(Data_Jobs!$L:$L,MATCH($A9,Data_Jobs!$A:$A,0)) -> In progress | E9: =INDEX(Data_Jobs!$K:$K,MATCH($A9,Data_Jobs!$A:$A,0)) -> 25580000 | F9: =SUMIFS('Cost Report'!$G$5:$G$180,'Cost Report'!$A$5:$A$180,$A9) -> 22973200 | G9: =SUMIFS('Cost Report'!$H$5:$H$180,'Cost Report'!$A$5:$A$180,$A9) -> 15913660 | H9: =SUMIFS('Cost Report'!$I$5:$I$180,'Cost Report'!$A$5:$A$180,$A9) -> 18195100 | I9: =SUMIFS('Cost Report'!$M$5:$M$180,'Cost Report'!$A$5:$A$180,$A9) -> 23781711 | J9: =I9-G9 -> 7868051.1 | K9: =IF(I9>0,G9/I9,0) -> 0.66915539 | L9: =E9*K9 -> 17116995 | M9: =SUMIFS(Data_Billings!$E:$E,Data_Billings!$D:$D,$A9) -> 18511138 | N9: =M9-L9 -> 1394142.8 | O9: =E9-I9 -> 1798288.8 | P9: =IF(E9>0,O9/E9,0) -> 0.070300577 | Q9: =INDEX(Data_Jobs!$H:$H,MATCH($A9,Data_Jobs!$A:$A,0)) -> 0.1 | R9: =P9-Q9 -> -0.029699423 | S9: =IF(G9>0,SUMIFS('Cost Report'!$K$5:$K$180,'Cost Report'!$A$5:$A$180,$A9)/G9,"") -> 0.96603098 | T9: =E9-L9 -> 8463005.2
A10: 25-112 | B10: =INDEX(Data_Jobs!$B:$B,MATCH($A10,Data_Jobs!$A:$A,0)) -> Fire Hall No. 4 | C10: =INDEX(Data_Jobs!$E:$E,MATCH($A10,Data_Jobs!$A:$A,0)) -> R. Singh | D10: =INDEX(Data_Jobs!$L:$L,MATCH($A10,Data_Jobs!$A:$A,0)) -> In progress | E10: =INDEX(Data_Jobs!$K:$K,MATCH($A10,Data_Jobs!$A:$A,0)) -> 9026000 | F10: =SUMIFS('Cost Report'!$G$5:$G$180,'Cost Report'!$A$5:$A$180,$A10) -> 7983600 | G10: =SUMIFS('Cost Report'!$H$5:$H$180,'Cost Report'!$A$5:$A$180,$A10) -> 7797690.6 | H10: =SUMIFS('Cost Report'!$I$5:$I$180,'Cost Report'!$A$5:$A$180,$A10) -> 6175300 | I10: =SUMIFS('Cost Report'!$M$5:$M$180,'Cost Report'!$A$5:$A$180,$A10) -> 8177299.8 | J10: =I10-G10 -> 379609.19 | K10: =IF(I10>0,G10/I10,0) -> 0.95357768 | L10: =E10*K10 -> 8606992.2 | M10: =SUMIFS(Data_Billings!$E:$E,Data_Billings!$D:$D,$A10) -> 8359789.8 | N10: =M10-L10 -> -247202.33 | O10: =E10-I10 -> 848700.19 | P10: =IF(E10>0,O10/E10,0) -> 0.094028383 | Q10: =INDEX(Data_Jobs!$H:$H,MATCH($A10,Data_Jobs!$A:$A,0)) -> 0.115 | R10: =P10-Q10 -> -0.020971617 | S10: =IF(G10>0,SUMIFS('Cost Report'!$K$5:$K$180,'Cost Report'!$A$5:$A$180,$A10)/G10,"") -> 0.98619229 | T10: =E10-L10 -> 419007.82
A11: 25-115 | B11: =INDEX(Data_Jobs!$B:$B,MATCH($A11,Data_Jobs!$A:$A,0)) -> Recreation Centre Retrofit | C11: =INDEX(Data_Jobs!$E:$E,MATCH($A11,Data_Jobs!$A:$A,0)) -> J. Tremblay | D11: =INDEX(Data_Jobs!$L:$L,MATCH($A11,Data_Jobs!$A:$A,0)) -> In progress | E11: =INDEX(Data_Jobs!$K:$K,MATCH($A11,Data_Jobs!$A:$A,0)) -> 12065000 | F11: =SUMIFS('Cost Report'!$G$5:$G$180,'Cost Report'!$A$5:$A$180,$A11) -> 10763600 | G11: =SUMIFS('Cost Report'!$H$5:$H$180,'Cost Report'!$A$5:$A$180,$A11) -> 8582224.5 | H11: =SUMIFS('Cost Report'!$I$5:$I$180,'Cost Report'!$A$5:$A$180,$A11) -> 8139000 | I11: =SUMIFS('Cost Report'!$M$5:$M$180,'Cost Report'!$A$5:$A$180,$A11) -> 11519732 | J11: =I11-G11 -> 2937507.8 | K11: =IF(I11>0,G11/I11,0) -> 0.74500208 | L11: =E11*K11 -> 8988450.1 | M11: =SUMIFS(Data_Billings!$E:$E,Data_Billings!$D:$D,$A11) -> 8294926 | N11: =M11-L11 -> -693524.07 | O11: =E11-I11 -> 545267.72 | P11: =IF(E11>0,O11/E11,0) -> 0.045194175 | Q11: =INDEX(Data_Jobs!$H:$H,MATCH($A11,Data_Jobs!$A:$A,0)) -> 0.105 | R11: =P11-Q11 -> -0.059805825 | S11: =IF(G11>0,SUMIFS('Cost Report'!$K$5:$K$180,'Cost Report'!$A$5:$A$180,$A11)/G11,"") -> 0.94292272 | T11: =E11-L11 -> 3076549.9
A12: 25-118 | B12: =INDEX(Data_Jobs!$B:$B,MATCH($A12,Data_Jobs!$A:$A,0)) -> Cold Storage Facility | C12: =INDEX(Data_Jobs!$E:$E,MATCH($A12,Data_Jobs!$A:$A,0)) -> S. Chen | D12: =INDEX(Data_Jobs!$L:$L,MATCH($A12,Data_Jobs!$A:$A,0)) -> In progress | E12: =INDEX(Data_Jobs!$K:$K,MATCH($A12,Data_Jobs!$A:$A,0)) -> 18090000 | F12: =SUMIFS('Cost Report'!$G$5:$G$180,'Cost Report'!$A$5:$A$180,$A12) -> 16302200 | G12: =SUMIFS('Cost Report'!$H$5:$H$180,'Cost Report'!$A$5:$A$180,$A12) -> 13092124 | H12: =SUMIFS('Cost Report'!$I$5:$I$180,'Cost Report'!$A$5:$A$180,$A12) -> 12660900 | I12: =SUMIFS('Cost Report'!$M$5:$M$180,'Cost Report'!$A$5:$A$180,$A12) -> 16233743 | J12: =I12-G12 -> 3141619 | K12: =IF(I12>0,G12/I12,0) -> 0.80647599 | L12: =E12*K12 -> 14589151 | M12: =SUMIFS(Data_Billings!$E:$E,Data_Billings!$D:$D,$A12) -> 15322118 | N12: =M12-L12 -> 732967.53 | O12: =E12-I12 -> 1856257 | P12: =IF(E12>0,O12/E12,0) -> 0.10261233 | Q12: =INDEX(Data_Jobs!$H:$H,MATCH($A12,Data_Jobs!$A:$A,0)) -> 0.098 | R12: =P12-Q12 -> 0.0046123293 | S12: =IF(G12>0,SUMIFS('Cost Report'!$K$5:$K$180,'Cost Report'!$A$5:$A$180,$A12)/G12,"") -> 1.0181287 | T12: =E12-L12 -> 3500849.3
A13: 25-121 | B13: =INDEX(Data_Jobs!$B:$B,MATCH($A13,Data_Jobs!$A:$A,0)) -> Seniors Residence | C13: =INDEX(Data_Jobs!$E:$E,MATCH($A13,Data_Jobs!$A:$A,0)) -> A. Dubois | D13: =INDEX(Data_Jobs!$L:$L,MATCH($A13,Data_Jobs!$A:$A,0)) -> In progress | E13: =INDEX(Data_Jobs!$K:$K,MATCH($A13,Data_Jobs!$A:$A,0)) -> 20405000 | F13: =SUMIFS('Cost Report'!$G$5:$G$180,'Cost Report'!$A$5:$A$180,$A13) -> 18541400 | G13: =SUMIFS('Cost Report'!$H$5:$H$180,'Cost Report'!$A$5:$A$180,$A13) -> 5364879.5 | H13: =SUMIFS('Cost Report'!$I$5:$I$180,'Cost Report'!$A$5:$A$180,$A13) -> 13169200 | I13: =SUMIFS('Cost Report'!$M$5:$M$180,'Cost Report'!$A$5:$A$180,$A13) -> 18538819 | J13: =I13-G13 -> 13173939 | K13: =IF(I13>0,G13/I13,0) -> 0.28938626 | L13: =E13*K13 -> 5904926.7 | M13: =SUMIFS(Data_Billings!$E:$E,Data_Billings!$D:$D,$A13) -> 6001562.8 | N13: =M13-L13 -> 96636.089 | O13: =E13-I13 -> 1866181.2 | P13: =IF(E13>0,O13/E13,0) -> 0.091457054 | Q13: =INDEX(Data_Jobs!$H:$H,MATCH($A13,Data_Jobs!$A:$A,0)) -> 0.09 | R13: =P13-Q13 -> 0.0014570538 | S13: =IF(G13>0,SUMIFS('Cost Report'!$K$5:$K$180,'Cost Report'!$A$5:$A$180,$A13)/G13,"") -> 1.0143912 | T13: =E13-L13 -> 14500073
A14: 26-124 | B14: =INDEX(Data_Jobs!$B:$B,MATCH($A14,Data_Jobs!$A:$A,0)) -> Process Building | C14: =INDEX(Data_Jobs!$E:$E,MATCH($A14,Data_Jobs!$A:$A,0)) -> M. Okafor | D14: =INDEX(Data_Jobs!$L:$L,MATCH($A14,Data_Jobs!$A:$A,0)) -> In progress | E14: =INDEX(Data_Jobs!$K:$K,MATCH($A14,Data_Jobs!$A:$A,0)) -> 13400000 | F14: =SUMIFS('Cost Report'!$G$5:$G$180,'Cost Report'!$A$5:$A$180,$A14) -> 11858900 | G14: =SUMIFS('Cost Report'!$H$5:$H$180,'Cost Report'!$A$5:$A$180,$A14) -> 5372210.8 | H14: =SUMIFS('Cost Report'!$I$5:$I$180,'Cost Report'!$A$5:$A$180,$A14) -> 9211200 | I14: =SUMIFS('Cost Report'!$M$5:$M$180,'Cost Report'!$A$5:$A$180,$A14) -> 11951246 | J14: =I14-G14 -> 6579034.9 | K14: =IF(I14>0,G14/I14,0) -> 0.44951053 | L14: =E14*K14 -> 6023441.1 | M14: =SUMIFS(Data_Billings!$E:$E,Data_Billings!$D:$D,$A14) -> 6611526.6 | N14: =M14-L14 -> 588085.47 | O14: =E14-I14 -> 1448754.2 | P14: =IF(E14>0,O14/E14,0) -> 0.10811599 | Q14: =INDEX(Data_Jobs!$H:$H,MATCH($A14,Data_Jobs!$A:$A,0)) -> 0.115 | R14: =P14-Q14 -> -0.0068840141 | S14: =IF(G14>0,SUMIFS('Cost Report'!$K$5:$K$180,'Cost Report'!$A$5:$A$180,$A14)/G14,"") -> 0.99685378 | T14: =E14-L14 -> 7376558.9
A15: 26-127 | B15: =INDEX(Data_Jobs!$B:$B,MATCH($A15,Data_Jobs!$A:$A,0)) -> Retail Plaza | C15: =INDEX(Data_Jobs!$E:$E,MATCH($A15,Data_Jobs!$A:$A,0)) -> A. Dubois | D15: =INDEX(Data_Jobs!$L:$L,MATCH($A15,Data_Jobs!$A:$A,0)) -> In progress | E15: =INDEX(Data_Jobs!$K:$K,MATCH($A15,Data_Jobs!$A:$A,0)) -> 7650000 | F15: =SUMIFS('Cost Report'!$G$5:$G$180,'Cost Report'!$A$5:$A$180,$A15) -> 6693800 | G15: =SUMIFS('Cost Report'!$H$5:$H$180,'Cost Report'!$A$5:$A$180,$A15) -> 2201288.5 | H15: =SUMIFS('Cost Report'!$I$5:$I$180,'Cost Report'!$A$5:$A$180,$A15) -> 5000900 | I15: =SUMIFS('Cost Report'!$M$5:$M$180,'Cost Report'!$A$5:$A$180,$A15) -> 6607426.2 | J15: =I15-G15 -> 4406137.7 | K15: =IF(I15>0,G15/I15,0) -> 0.33315371 | L15: =E15*K15 -> 2548625.8 | M15: =SUMIFS(Data_Billings!$E:$E,Data_Billings!$D:$D,$A15) -> 2627509.3 | N15: =M15-L15 -> 78883.415 | O15: =E15-I15 -> 1042573.8 | P15: =IF(E15>0,O15/E15,0) -> 0.13628415 | Q15: =INDEX(Data_Jobs!$H:$H,MATCH($A15,Data_Jobs!$A:$A,0)) -> 0.125 | R15: =P15-Q15 -> 0.011284153 | S15: =IF(G15>0,SUMIFS('Cost Report'!$K$5:$K$180,'Cost Report'!$A$5:$A$180,$A15)/G15,"") -> 1.0346956 | T15: =E15-L15 -> 5101374.2
A16: 26-130 | B16: =INDEX(Data_Jobs!$B:$B,MATCH($A16,Data_Jobs!$A:$A,0)) -> Public Works Yard Building | C16: =INDEX(Data_Jobs!$E:$E,MATCH($A16,Data_Jobs!$A:$A,0)) -> R. Singh | D16: =INDEX(Data_Jobs!$L:$L,MATCH($A16,Data_Jobs!$A:$A,0)) -> In progress | E16: =INDEX(Data_Jobs!$K:$K,MATCH($A16,Data_Jobs!$A:$A,0)) -> 6300000 | F16: =SUMIFS('Cost Report'!$G$5:$G$180,'Cost Report'!$A$5:$A$180,$A16) -> 5607100 | G16: =SUMIFS('Cost Report'!$H$5:$H$180,'Cost Report'!$A$5:$A$180,$A16) -> 540737.58 | H16: =SUMIFS('Cost Report'!$I$5:$I$180,'Cost Report'!$A$5:$A$180,$A16) -> 3486800 | I16: =SUMIFS('Cost Report'!$M$5:$M$180,'Cost Report'!$A$5:$A$180,$A16) -> 5598962.3 | J16: =I16-G16 -> 5058224.7 | K16: =IF(I16>0,G16/I16,0) -> 0.096578179 | L16: =E16*K16 -> 608442.53 | M16: =SUMIFS(Data_Billings!$E:$E,Data_Billings!$D:$D,$A16) -> 614815.4 | N16: =M16-L16 -> 6372.8714 | O16: =E16-I16 -> 701037.74 | P16: =IF(E16>0,O16/E16,0) -> 0.11127583 | Q16: =INDEX(Data_Jobs!$H:$H,MATCH($A16,Data_Jobs!$A:$A,0)) -> 0.11 | R16: =P16-Q16 -> 0.001275832 | S16: =IF(G16>0,SUMIFS('Cost Report'!$K$5:$K$180,'Cost Report'!$A$5:$A$180,$A16)/G16,"") -> 1.0236786 | T16: =E16-L16 -> 5691557.5
A17: Portfolio total | E17: =SUM(E5:E16) -> 176921000 | F17: =SUM(F5:F16) -> 158253700 | G17: =SUM(G5:G16) -> 1.1457826e+08 | H17: =SUM(H5:H16) -> 120824700 | I17: =SUM(I5:I16) -> 1.608244e+08 | J17: =SUM(J5:J16) -> 46246134 | K17: =G17/I17 -> 0.7124433 | L17: =SUM(L5:L16) -> 1.2583805e+08 | M17: =SUM(M5:M16) -> 1.2825487e+08 | N17: =SUM(N5:N16) -> 2416818.1 | O17: =SUM(O5:O16) -> 16096602 | P17: =O17/E17 -> 0.090981862 | Q17: =SUMPRODUCT(Q5:Q16,E5:E16)/E17 -> 0.10421318 | R17: =P17-Q17 -> -0.013231318 | S17: ='Cost Report'!L181 -> 0.99250323 | T17: =SUM(T5:T16) -> 51082948
A19: Red: margin fade worse than -2.0 pts, or CPI below 0.97. Over/(under) billing: positive = billings in excess of revenue (liability); negative = revenue in excess of billings (asset).
A20: Green text = pulled from the job master (Data_Jobs). All other figures are formulas on the Cost Report and Data_ tabs.

Sheet Job Detail
A1: Job Cost Detail
A2: Pick a job number from the yellow drop-down to refresh this page.
B3: Job: | C3: 25-115 | D3: =INDEX(Data_Jobs!$B:$B,MATCH($C$3,Data_Jobs!$A:$A,0)) -> Recreation Centre Retrofit
C5: Project manager | D5: =INDEX(Data_Jobs!$E:$E,MATCH($C$3,Data_Jobs!$A:$A,0)) -> J. Tremblay | F5: Revised contract | H5: =INDEX(Data_Jobs!$K:$K,MATCH($C$3,Data_Jobs!$A:$A,0)) -> 12065000 | J5: Job CPI | M5: =IF(H27>0,K27/H27,0) -> 0.94292272
C6: Client type | D6: =INDEX(Data_Jobs!$D:$D,MATCH($C$3,Data_Jobs!$A:$A,0)) -> Municipal | F6: Forecast cost (EAC) | H6: =M27 -> 11519732 | J6: Labour productivity | M6: =IF(Q27>0,R27/Q27,0) -> 0.89317789
C7: Status | D7: =INDEX(Data_Jobs!$L:$L,MATCH($C$3,Data_Jobs!$A:$A,0)) -> In progress | F7: Projected margin | H7: =IF(H5>0,(H5-H6)/H5,0) -> 0.045194175 | J7: Forecast over budget | M7: =-SUMIF(N12:N26,"<0") -> 790532.28
C8: Scheduled finish | D8: =INDEX(Data_Jobs!$J:$J,MATCH($C$3,Data_Jobs!$A:$A,0)) -> 2027-03-26 | F8: Bid margin | H8: =INDEX(Data_Jobs!$H:$H,MATCH($C$3,Data_Jobs!$A:$A,0)) -> 0.105 | J8: Cost to complete | M8: =O27 -> 2937507.8
F9: Margin fade | H9: =H7-H8 -> -0.059805825
B11: Cost Code | C11: Description | D11: Cost Type | E11: Original Budget | F11: Budget Changes | G11: Revised Budget | H11: Actual Cost | I11: Committed | J11: % Complete | K11: Earned Value | L11: CPI | M11: Forecast Cost (EAC) | N11: Variance at Completion | O11: Cost to Complete | P11: Budget Hours | Q11: Actual Hours | R11: Earned Hours
B12: 01-100 | C12: =INDEX(Data_CostCodes!$B:$B,MATCH($B12,Data_CostCodes!$A:$A,0)) -> General Conditions - Supervision | D12: =INDEX(Data_CostCodes!$D:$D,MATCH($B12,Data_CostCodes!$A:$A,0)) -> Labour | E12: =SUMIFS('Cost Report'!$E$5:$E$180,'Cost Report'!$A$5:$A$180,$C$3,'Cost Report'!$B$5:$B$180,$B12) -> 957900 | F12: =SUMIFS('Cost Report'!$F$5:$F$180,'Cost Report'!$A$5:$A$180,$C$3,'Cost Report'!$B$5:$B$180,$B12) -> 0 | G12: =SUMIFS('Cost Report'!$G$5:$G$180,'Cost Report'!$A$5:$A$180,$C$3,'Cost Report'!$B$5:$B$180,$B12) -> 957900 | H12: =SUMIFS('Cost Report'!$H$5:$H$180,'Cost Report'!$A$5:$A$180,$C$3,'Cost Report'!$B$5:$B$180,$B12) -> 766276.35 | I12: =SUMIFS('Cost Report'!$I$5:$I$180,'Cost Report'!$A$5:$A$180,$C$3,'Cost Report'!$B$5:$B$180,$B12) -> 0 | J12: =IF(G12>0,K12/G12,0) -> 0.763 | K12: =SUMIFS('Cost Report'!$K$5:$K$180,'Cost Report'!$A$5:$A$180,$C$3,'Cost Report'!$B$5:$B$180,$B12) -> 730877.7 | L12: =IF(H12>0,K12/H12,"") -> 0.95380433 | M12: =SUMIFS('Cost Report'!$M$5:$M$180,'Cost Report'!$A$5:$A$180,$C$3,'Cost Report'!$B$5:$B$180,$B12) -> 1004294 | N12: =SUMIFS('Cost Report'!$N$5:$N$180,'Cost Report'!$A$5:$A$180,$C$3,'Cost Report'!$B$5:$B$180,$B12) -> -46394.037 | O12: =SUMIFS('Cost Report'!$O$5:$O$180,'Cost Report'!$A$5:$A$180,$C$3,'Cost Report'!$B$5:$B$180,$B12) -> 238017.69 | P12: =SUMIFS('Cost Report'!$P$5:$P$180,'Cost Report'!$A$5:$A$180,$C$3,'Cost Report'!$B$5:$B$180,$B12) -> 10412 | Q12: =SUMIFS('Cost Report'!$Q$5:$Q$180,'Cost Report'!$A$5:$A$180,$C$3,'Cost Report'!$B$5:$B$180,$B12) -> 8329 | R12: =SUMIFS('Cost Report'!$R$5:$R$180,'Cost Report'!$A$5:$A$180,$C$3,'Cost Report'!$B$5:$B$180,$B12) -> 7944.356
B13: 01-200 | C13: =INDEX(Data_CostCodes!$B:$B,MATCH($B13,Data_CostCodes!$A:$A,0)) -> Site Facilities & Temp Services | D13: =INDEX(Data_CostCodes!$D:$D,MATCH($B13,Data_CostCodes!$A:$A,0)) -> Other | E13: =SUMIFS('Cost Report'!$E$5:$E$180,'Cost Report'!$A$5:$A$180,$C$3,'Cost Report'!$B$5:$B$180,$B13) -> 313200 | F13: =SUMIFS('Cost Report'!$F$5:$F$180,'Cost Report'!$A$5:$A$180,$C$3,'Cost Report'!$B$5:$B$180,$B13) -> 43300 | G13: =SUMIFS('Cost Report'!$G$5:$G$180,'Cost Report'!$A$5:$A$180,$C$3,'Cost Report'!$B$5:$B$180,$B13) -> 356500 | H13: =SUMIFS('Cost Report'!$H$5:$H$180,'Cost Report'!$A$5:$A$180,$C$3,'Cost Report'!$B$5:$B$180,$B13) -> 275153.11 | I13: =SUMIFS('Cost Report'!$I$5:$I$180,'Cost Report'!$A$5:$A$180,$C$3,'Cost Report'!$B$5:$B$180,$B13) -> 0 | J13: =IF(G13>0,K13/G13,0) -> 0.743 | K13: =SUMIFS('Cost Report'!$K$5:$K$180,'Cost Report'!$A$5:$A$180,$C$3,'Cost Report'!$B$5:$B$180,$B13) -> 264879.5 | L13: =IF(H13>0,K13/H13,"") -> 0.96266221 | M13: =SUMIFS('Cost Report'!$M$5:$M$180,'Cost Report'!$A$5:$A$180,$C$3,'Cost Report'!$B$5:$B$180,$B13) -> 370327.2 | N13: =SUMIFS('Cost Report'!$N$5:$N$180,'Cost Report'!$A$5:$A$180,$C$3,'Cost Report'!$B$5:$B$180,$B13) -> -13827.201 | O13: =SUMIFS('Cost Report'!$O$5:$O$180,'Cost Report'!$A$5:$A$180,$C$3,'Cost Report'!$B$5:$B$180,$B13) -> 95174.091 | P13: =SUMIFS('Cost Report'!$P$5:$P$180,'Cost Report'!$A$5:$A$180,$C$3,'Cost Report'!$B$5:$B$180,$B13) -> 0 | Q13: =SUMIFS('Cost Report'!$Q$5:$Q$180,'Cost Report'!$A$5:$A$180,$C$3,'Cost Report'!$B$5:$B$180,$B13) -> 0 | R13: =SUMIFS('Cost Report'!$R$5:$R$180,'Cost Report'!$A$5:$A$180,$C$3,'Cost Report'!$B$5:$B$180,$B13) -> 0
B14: 01-500 | C14: =INDEX(Data_CostCodes!$B:$B,MATCH($B14,Data_CostCodes!$A:$A,0)) -> Equipment Rental | D14: =INDEX(Data_CostCodes!$D:$D,MATCH($B14,Data_CostCodes!$A:$A,0)) -> Equipment | E14: =SUMIFS('Cost Report'!$E$5:$E$180,'Cost Report'!$A$5:$A$180,$C$3,'Cost Report'!$B$5:$B$180,$B14) -> 275800 | F14: =SUMIFS('Cost Report'!$F$5:$F$180,'Cost Report'!$A$5:$A$180,$C$3,'Cost Report'!$B$5:$B$180,$B14) -> 0 | G14: =SUMIFS('Cost Report'!$G$5:$G$180,'Cost Report'!$A$5:$A$180,$C$3,'Cost Report'!$B$5:$B$180,$B14) -> 275800 | H14: =SUMIFS('Cost Report'!$H$5:$H$180,'Cost Report'!$A$5:$A$180,$C$3,'Cost Report'!$B$5:$B$180,$B14) -> 267801.12 | I14: =SUMIFS('Cost Report'!$I$5:$I$180,'Cost Report'!$A$5:$A$180,$C$3,'Cost Report'!$B$5:$B$180,$B14) -> 0 | J14: =IF(G14>0,K14/G14,0) -> 0.904 | K14: =SUMIFS('Cost Report'!$K$5:$K$180,'Cost Report'!$A$5:$A$180,$C$3,'Cost Report'!$B$5:$B$180,$B14) -> 249323.2 | L14: =IF(H14>0,K14/H14,"") -> 0.93100133 | M14: =SUMIFS('Cost Report'!$M$5:$M$180,'Cost Report'!$A$5:$A$180,$C$3,'Cost Report'!$B$5:$B$180,$B14) -> 296240.18 | N14: =SUMIFS('Cost Report'!$N$5:$N$180,'Cost Report'!$A$5:$A$180,$C$3,'Cost Report'!$B$5:$B$180,$B14) -> -20440.177 | O14: =SUMIFS('Cost Report'!$O$5:$O$180,'Cost Report'!$A$5:$A$180,$C$3,'Cost Report'!$B$5:$B$180,$B14) -> 28439.057 | P14: =SUMIFS('Cost Report'!$P$5:$P$180,'Cost Report'!$A$5:$A$180,$C$3,'Cost Report'!$B$5:$B$180,$B14) -> 0 | Q14: =SUMIFS('Cost Report'!$Q$5:$Q$180,'Cost Report'!$A$5:$A$180,$C$3,'Cost Report'!$B$5:$B$180,$B14) -> 0 | R14: =SUMIFS('Cost Report'!$R$5:$R$180,'Cost Report'!$A$5:$A$180,$C$3,'Cost Report'!$B$5:$B$180,$B14) -> 0
B15: 02-200 | C15: =INDEX(Data_CostCodes!$B:$B,MATCH($B15,Data_CostCodes!$A:$A,0)) -> Earthwork & Excavation | D15: =INDEX(Data_CostCodes!$D:$D,MATCH($B15,Data_CostCodes!$A:$A,0)) -> Subcontract | E15: =SUMIFS('Cost Report'!$E$5:$E$180,'Cost Report'!$A$5:$A$180,$C$3,'Cost Report'!$B$5:$B$180,$B15) -> 410500 | F15: =SUMIFS('Cost Report'!$F$5:$F$180,'Cost Report'!$A$5:$A$180,$C$3,'Cost Report'!$B$5:$B$180,$B15) -> 0 | G15: =SUMIFS('Cost Report'!$G$5:$G$180,'Cost Report'!$A$5:$A$180,$C$3,'Cost Report'!$B$5:$B$180,$B15) -> 410500 | H15: =SUMIFS('Cost Report'!$H$5:$H$180,'Cost Report'!$A$5:$A$180,$C$3,'Cost Report'!$B$5:$B$180,$B15) -> 395353.03 | I15: =SUMIFS('Cost Report'!$I$5:$I$180,'Cost Report'!$A$5:$A$180,$C$3,'Cost Report'!$B$5:$B$180,$B15) -> 396500 | J15: =IF(G15>0,K15/G15,0) -> 1 | K15: =SUMIFS('Cost Report'!$K$5:$K$180,'Cost Report'!$A$5:$A$180,$C$3,'Cost Report'!$B$5:$B$180,$B15) -> 410500 | L15: =IF(H15>0,K15/H15,"") -> 1.0383125 | M15: =SUMIFS('Cost Report'!$M$5:$M$180,'Cost Report'!$A$5:$A$180,$C$3,'Cost Report'!$B$5:$B$180,$B15) -> 396500 | N15: =SUMIFS('Cost Report'!$N$5:$N$180,'Cost Report'!$A$5:$A$180,$C$3,'Cost Report'!$B$5:$B$180,$B15) -> 14000 | O15: =SUMIFS('Cost Report'!$O$5:$O$180,'Cost Report'!$A$5:$A$180,$C$3,'Cost Report'!$B$5:$B$180,$B15) -> 1146.97 | P15: =SUMIFS('Cost Report'!$P$5:$P$180,'Cost Report'!$A$5:$A$180,$C$3,'Cost Report'!$B$5:$B$180,$B15) -> 0 | Q15: =SUMIFS('Cost Report'!$Q$5:$Q$180,'Cost Report'!$A$5:$A$180,$C$3,'Cost Report'!$B$5:$B$180,$B15) -> 0 | R15: =SUMIFS('Cost Report'!$R$5:$R$180,'Cost Report'!$A$5:$A$180,$C$3,'Cost Report'!$B$5:$B$180,$B15) -> 0
B16: 03-100 | C16: =INDEX(Data_CostCodes!$B:$B,MATCH($B16,Data_CostCodes!$A:$A,0)) -> Concrete Formwork | D16: =INDEX(Data_CostCodes!$D:$D,MATCH($B16,Data_CostCodes!$A:$A,0)) -> Labour | E16: =SUMIFS('Cost Report'!$E$5:$E$180,'Cost Report'!$A$5:$A$180,$C$3,'Cost Report'!$B$5:$B$180,$B16) -> 545200 | F16: =SUMIFS('Cost Report'!$F$5:$F$180,'Cost Report'!$A$5:$A$180,$C$3,'Cost Report'!$B$5:$B$180,$B16) -> 549300 | G16: =SUMIFS('Cost Report'!$G$5:$G$180,'Cost Report'!$A$5:$A$180,$C$3,'Cost Report'!$B$5:$B$180,$B16) -> 1094500 | H16: =SUMIFS('Cost Report'!$H$5:$H$180,'Cost Report'!$A$5:$A$180,$C$3,'Cost Report'!$B$5:$B$180,$B16) -> 1229218.8 | I16: =SUMIFS('Cost Report'!$I$5:$I$180,'Cost Report'!$A$5:$A$180,$C$3,'Cost Report'!$B$5:$B$180,$B16) -> 0 | J16: =IF(G16>0,K16/G16,0) -> 1 | K16: =SUMIFS('Cost Report'!$K$5:$K$180,'Cost Report'!$A$5:$A$180,$C$3,'Cost Report'!$B$5:$B$180,$B16) -> 1094500 | L16: =IF(H16>0,K16/H16,"") -> 0.89040289 | M16: =SUMIFS('Cost Report'!$M$5:$M$180,'Cost Report'!$A$5:$A$180,$C$3,'Cost Report'!$B$5:$B$180,$B16) -> 1229218.8 | N16: =SUMIFS('Cost Report'!$N$5:$N$180,'Cost Report'!$A$5:$A$180,$C$3,'Cost Report'!$B$5:$B$180,$B16) -> -134718.83 | O16: =SUMIFS('Cost Report'!$O$5:$O$180,'Cost Report'!$A$5:$A$180,$C$3,'Cost Report'!$B$5:$B$180,$B16) -> 0 | P16: =SUMIFS('Cost Report'!$P$5:$P$180,'Cost Report'!$A$5:$A$180,$C$3,'Cost Report'!$B$5:$B$180,$B16) -> 14791 | Q16: =SUMIFS('Cost Report'!$Q$5:$Q$180,'Cost Report'!$A$5:$A$180,$C$3,'Cost Report'!$B$5:$B$180,$B16) -> 16611.2 | R16: =SUMIFS('Cost Report'!$R$5:$R$180,'Cost Report'!$A$5:$A$180,$C$3,'Cost Report'!$B$5:$B$180,$B16) -> 14791
B17: 03-200 | C17: =INDEX(Data_CostCodes!$B:$B,MATCH($B17,Data_CostCodes!$A:$A,0)) -> Reinforcing Steel | D17: =INDEX(Data_CostCodes!$D:$D,MATCH($B17,Data_CostCodes!$A:$A,0)) -> Material | E17: =SUMIFS('Cost Report'!$E$5:$E$180,'Cost Report'!$A$5:$A$180,$C$3,'Cost Report'!$B$5:$B$180,$B17) -> 452600 | F17: =SUMIFS('Cost Report'!$F$5:$F$180,'Cost Report'!$A$5:$A$180,$C$3,'Cost Report'!$B$5:$B$180,$B17) -> 0 | G17: =SUMIFS('Cost Report'!$G$5:$G$180,'Cost Report'!$A$5:$A$180,$C$3,'Cost Report'!$B$5:$B$180,$B17) -> 452600 | H17: =SUMIFS('Cost Report'!$H$5:$H$180,'Cost Report'!$A$5:$A$180,$C$3,'Cost Report'!$B$5:$B$180,$B17) -> 446285.28 | I17: =SUMIFS('Cost Report'!$I$5:$I$180,'Cost Report'!$A$5:$A$180,$C$3,'Cost Report'!$B$5:$B$180,$B17) -> 456400 | J17: =IF(G17>0,K17/G17,0) -> 1 | K17: =SUMIFS('Cost Report'!$K$5:$K$180,'Cost Report'!$A$5:$A$180,$C$3,'Cost Report'!$B$5:$B$180,$B17) -> 452600 | L17: =IF(H17>0,K17/H17,"") -> 1.0141495 | M17: =SUMIFS('Cost Report'!$M$5:$M$180,'Cost Report'!$A$5:$A$180,$C$3,'Cost Report'!$B$5:$B$180,$B17) -> 456400 | N17: =SUMIFS('Cost Report'!$N$5:$N$180,'Cost Report'!$A$5:$A$180,$C$3,'Cost Report'!$B$5:$B$180,$B17) -> -3800 | O17: =SUMIFS('Cost Report'!$O$5:$O$180,'Cost Report'!$A$5:$A$180,$C$3,'Cost Report'!$B$5:$B$180,$B17) -> 10114.72 | P17: =SUMIFS('Cost Report'!$P$5:$P$180,'Cost Report'!$A$5:$A$180,$C$3,'Cost Report'!$B$5:$B$180,$B17) -> 0 | Q17: =SUMIFS('Cost Report'!$Q$5:$Q$180,'Cost Report'!$A$5:$A$180,$C$3,'Cost Report'!$B$5:$B$180,$B17) -> 0 | R17: =SUMIFS('Cost Report'!$R$5:$R$180,'Cost Report'!$A$5:$A$180,$C$3,'Cost Report'!$B$5:$B$180,$B17) -> 0
B18: 03-300 | C18: =INDEX(Data_CostCodes!$B:$B,MATCH($B18,Data_CostCodes!$A:$A,0)) -> Cast-in-Place Concrete | D18: =INDEX(Data_CostCodes!$D:$D,MATCH($B18,Data_CostCodes!$A:$A,0)) -> Material | E18: =SUMIFS('Cost Report'!$E$5:$E$180,'Cost Report'!$A$5:$A$180,$C$3,'Cost Report'!$B$5:$B$180,$B18) -> 763100 | F18: =SUMIFS('Cost Report'!$F$5:$F$180,'Cost Report'!$A$5:$A$180,$C$3,'Cost Report'!$B$5:$B$180,$B18) -> 0 | G18: =SUMIFS('Cost Report'!$G$5:$G$180,'Cost Report'!$A$5:$A$180,$C$3,'Cost Report'!$B$5:$B$180,$B18) -> 763100 | H18: =SUMIFS('Cost Report'!$H$5:$H$180,'Cost Report'!$A$5:$A$180,$C$3,'Cost Report'!$B$5:$B$180,$B18) -> 756596.67 | I18: =SUMIFS('Cost Report'!$I$5:$I$180,'Cost Report'!$A$5:$A$180,$C$3,'Cost Report'!$B$5:$B$180,$B18) -> 767600 | J18: =IF(G18>0,K18/G18,0) -> 1 | K18: =SUMIFS('Cost Report'!$K$5:$K$180,'Cost Report'!$A$5:$A$180,$C$3,'Cost Report'!$B$5:$B$180,$B18) -> 763100 | L18: =IF(H18>0,K18/H18,"") -> 1.0085955 | M18: =SUMIFS('Cost Report'!$M$5:$M$180,'Cost Report'!$A$5:$A$180,$C$3,'Cost Report'!$B$5:$B$180,$B18) -> 767600 | N18: =SUMIFS('Cost Report'!$N$5:$N$180,'Cost Report'!$A$5:$A$180,$C$3,'Cost Report'!$B$5:$B$180,$B18) -> -4500 | O18: =SUMIFS('Cost Report'!$O$5:$O$180,'Cost Report'!$A$5:$A$180,$C$3,'Cost Report'!$B$5:$B$180,$B18) -> 11003.33 | P18: =SUMIFS('Cost Report'!$P$5:$P$180,'Cost Report'!$A$5:$A$180,$C$3,'Cost Report'!$B$5:$B$180,$B18) -> 0 | Q18: =SUMIFS('Cost Report'!$Q$5:$Q$180,'Cost Report'!$A$5:$A$180,$C$3,'Cost Report'!$B$5:$B$180,$B18) -> 0 | R18: =SUMIFS('Cost Report'!$R$5:$R$180,'Cost Report'!$A$5:$A$180,$C$3,'Cost Report'!$B$5:$B$180,$B18) -> 0
B19: 04-200 | C19: =INDEX(Data_CostCodes!$B:$B,MATCH($B19,Data_CostCodes!$A:$A,0)) -> Masonry | D19: =INDEX(Data_CostCodes!$D:$D,MATCH($B19,Data_CostCodes!$A:$A,0)) -> Subcontract | E19: =SUMIFS('Cost Report'!$E$5:$E$180,'Cost Report'!$A$5:$A$180,$C$3,'Cost Report'!$B$5:$B$180,$B19) -> 789900 | F19: =SUMIFS('Cost Report'!$F$5:$F$180,'Cost Report'!$A$5:$A$180,$C$3,'Cost Report'!$B$5:$B$180,$B19) -> 0 | G19: =SUMIFS('Cost Report'!$G$5:$G$180,'Cost Report'!$A$5:$A$180,$C$3,'Cost Report'!$B$5:$B$180,$B19) -> 789900 | H19: =SUMIFS('Cost Report'!$H$5:$H$180,'Cost Report'!$A$5:$A$180,$C$3,'Cost Report'!$B$5:$B$180,$B19) -> 808032.22 | I19: =SUMIFS('Cost Report'!$I$5:$I$180,'Cost Report'!$A$5:$A$180,$C$3,'Cost Report'!$B$5:$B$180,$B19) -> 811100 | J19: =IF(G19>0,K19/G19,0) -> 1 | K19: =SUMIFS('Cost Report'!$K$5:$K$180,'Cost Report'!$A$5:$A$180,$C$3,'Cost Report'!$B$5:$B$180,$B19) -> 789900 | L19: =IF(H19>0,K19/H19,"") -> 0.97756003 | M19: =SUMIFS('Cost Report'!$M$5:$M$180,'Cost Report'!$A$5:$A$180,$C$3,'Cost Report'!$B$5:$B$180,$B19) -> 811100 | N19: =SUMIFS('Cost Report'!$N$5:$N$180,'Cost Report'!$A$5:$A$180,$C$3,'Cost Report'!$B$5:$B$180,$B19) -> -21200 | O19: =SUMIFS('Cost Report'!$O$5:$O$180,'Cost Report'!$A$5:$A$180,$C$3,'Cost Report'!$B$5:$B$180,$B19) -> 3067.78 | P19: =SUMIFS('Cost Report'!$P$5:$P$180,'Cost Report'!$A$5:$A$180,$C$3,'Cost Report'!$B$5:$B$180,$B19) -> 0 | Q19: =SUMIFS('Cost Report'!$Q$5:$Q$180,'Cost Report'!$A$5:$A$180,$C$3,'Cost Report'!$B$5:$B$180,$B19) -> 0 | R19: =SUMIFS('Cost Report'!$R$5:$R$180,'Cost Report'!$A$5:$A$180,$C$3,'Cost Report'!$B$5:$B$180,$B19) -> 0
B20: 05-100 | C20: =INDEX(Data_CostCodes!$B:$B,MATCH($B20,Data_CostCodes!$A:$A,0)) -> Structural Steel | D20: =INDEX(Data_CostCodes!$D:$D,MATCH($B20,Data_CostCodes!$A:$A,0)) -> Subcontract | E20: =SUMIFS('Cost Report'!$E$5:$E$180,'Cost Report'!$A$5:$A$180,$C$3,'Cost Report'!$B$5:$B$180,$B20) -> 730300 | F20: =SUMIFS('Cost Report'!$F$5:$F$180,'Cost Report'!$A$5:$A$180,$C$3,'Cost Report'!$B$5:$B$180,$B20) -> 0 | G20: =SUMIFS('Cost Report'!$G$5:$G$180,'Cost Report'!$A$5:$A$180,$C$3,'Cost Report'!$B$5:$B$180,$B20) -> 730300 | H20: =SUMIFS('Cost Report'!$H$5:$H$180,'Cost Report'!$A$5:$A$180,$C$3,'Cost Report'!$B$5:$B$180,$B20) -> 731077.8 | I20: =SUMIFS('Cost Report'!$I$5:$I$180,'Cost Report'!$A$5:$A$180,$C$3,'Cost Report'!$B$5:$B$180,$B20) -> 735800 | J20: =IF(G20>0,K20/G20,0) -> 1 | K20: =SUMIFS('Cost Report'!$K$5:$K$180,'Cost Report'!$A$5:$A$180,$C$3,'Cost Report'!$B$5:$B$180,$B20) -> 730300 | L20: =IF(H20>0,K20/H20,"") -> 0.99893609 | M20: =SUMIFS('Cost Report'!$M$5:$M$180,'Cost Report'!$A$5:$A$180,$C$3,'Cost Report'!$B$5:$B$180,$B20) -> 735800 | N20: =SUMIFS('Cost Report'!$N$5:$N$180,'Cost Report'!$A$5:$A$180,$C$3,'Cost Report'!$B$5:$B$180,$B20) -> -5500 | O20: =SUMIFS('Cost Report'!$O$5:$O$180,'Cost Report'!$A$5:$A$180,$C$3,'Cost Report'!$B$5:$B$180,$B20) -> 4722.2 | P20: =SUMIFS('Cost Report'!$P$5:$P$180,'Cost Report'!$A$5:$A$180,$C$3,'Cost Report'!$B$5:$B$180,$B20) -> 0 | Q20: =SUMIFS('Cost Report'!$Q$5:$Q$180,'Cost Report'!$A$5:$A$180,$C$3,'Cost Report'!$B$5:$B$180,$B20) -> 0 | R20: =SUMIFS('Cost Report'!$R$5:$R$180,'Cost Report'!$A$5:$A$180,$C$3,'Cost Report'!$B$5:$B$180,$B20) -> 0
B21: 06-100 | C21: =INDEX(Data_CostCodes!$B:$B,MATCH($B21,Data_CostCodes!$A:$A,0)) -> Rough Carpentry | D21: =INDEX(Data_CostCodes!$D:$D,MATCH($B21,Data_CostCodes!$A:$A,0)) -> Labour | E21: =SUMIFS('Cost Report'!$E$5:$E$180,'Cost Report'!$A$5:$A$180,$C$3,'Cost Report'!$B$5:$B$180,$B21) -> 385900 | F21: =SUMIFS('Cost Report'!$F$5:$F$180,'Cost Report'!$A$5:$A$180,$C$3,'Cost Report'!$B$5:$B$180,$B21) -> 0 | G21: =SUMIFS('Cost Report'!$G$5:$G$180,'Cost Report'!$A$5:$A$180,$C$3,'Cost Report'!$B$5:$B$180,$B21) -> 385900 | H21: =SUMIFS('Cost Report'!$H$5:$H$180,'Cost Report'!$A$5:$A$180,$C$3,'Cost Report'!$B$5:$B$180,$B21) -> 360969.68 | I21: =SUMIFS('Cost Report'!$I$5:$I$180,'Cost Report'!$A$5:$A$180,$C$3,'Cost Report'!$B$5:$B$180,$B21) -> 0 | J21: =IF(G21>0,K21/G21,0) -> 0.751 | K21: =SUMIFS('Cost Report'!$K$5:$K$180,'Cost Report'!$A$5:$A$180,$C$3,'Cost Report'!$B$5:$B$180,$B21) -> 289810.9 | L21: =IF(H21>0,K21/H21,"") -> 0.80286771 | M21: =SUMIFS('Cost Report'!$M$5:$M$180,'Cost Report'!$A$5:$A$180,$C$3,'Cost Report'!$B$5:$B$180,$B21) -> 480652.04 | N21: =SUMIFS('Cost Report'!$N$5:$N$180,'Cost Report'!$A$5:$A$180,$C$3,'Cost Report'!$B$5:$B$180,$B21) -> -94752.037 | O21: =SUMIFS('Cost Report'!$O$5:$O$180,'Cost Report'!$A$5:$A$180,$C$3,'Cost Report'!$B$5:$B$180,$B21) -> 119682.36 | P21: =SUMIFS('Cost Report'!$P$5:$P$180,'Cost Report'!$A$5:$A$180,$C$3,'Cost Report'!$B$5:$B$180,$B21) -> 5435 | Q21: =SUMIFS('Cost Report'!$Q$5:$Q$180,'Cost Report'!$A$5:$A$180,$C$3,'Cost Report'!$B$5:$B$180,$B21) -> 5084.1 | R21: =SUMIFS('Cost Report'!$R$5:$R$180,'Cost Report'!$A$5:$A$180,$C$3,'Cost Report'!$B$5:$B$180,$B21) -> 4081.685
B22: 07-200 | C22: =INDEX(Data_CostCodes!$B:$B,MATCH($B22,Data_CostCodes!$A:$A,0)) -> Roofing & Insulation | D22: =INDEX(Data_CostCodes!$D:$D,MATCH($B22,Data_CostCodes!$A:$A,0)) -> Subcontract | E22: =SUMIFS('Cost Report'!$E$5:$E$180,'Cost Report'!$A$5:$A$180,$C$3,'Cost Report'!$B$5:$B$180,$B22) -> 647300 | F22: =SUMIFS('Cost Report'!$F$5:$F$180,'Cost Report'!$A$5:$A$180,$C$3,'Cost Report'!$B$5:$B$180,$B22) -> 57600 | G22: =SUMIFS('Cost Report'!$G$5:$G$180,'Cost Report'!$A$5:$A$180,$C$3,'Cost Report'!$B$5:$B$180,$B22) -> 704900 | H22: =SUMIFS('Cost Report'!$H$5:$H$180,'Cost Report'!$A$5:$A$180,$C$3,'Cost Report'!$B$5:$B$180,$B22) -> 657408.01 | I22: =SUMIFS('Cost Report'!$I$5:$I$180,'Cost Report'!$A$5:$A$180,$C$3,'Cost Report'!$B$5:$B$180,$B22) -> 705400 | J22: =IF(G22>0,K22/G22,0) -> 0.954 | K22: =SUMIFS('Cost Report'!$K$5:$K$180,'Cost Report'!$A$5:$A$180,$C$3,'Cost Report'!$B$5:$B$180,$B22) -> 672474.6 | L22: =IF(H22>0,K22/H22,"") -> 1.0229182 | M22: =SUMIFS('Cost Report'!$M$5:$M$180,'Cost Report'!$A$5:$A$180,$C$3,'Cost Report'!$B$5:$B$180,$B22) -> 705400 | N22: =SUMIFS('Cost Report'!$N$5:$N$180,'Cost Report'!$A$5:$A$180,$C$3,'Cost Report'!$B$5:$B$180,$B22) -> -500 | O22: =SUMIFS('Cost Report'!$O$5:$O$180,'Cost Report'!$A$5:$A$180,$C$3,'Cost Report'!$B$5:$B$180,$B22) -> 47991.99 | P22: =SUMIFS('Cost Report'!$P$5:$P$180,'Cost Report'!$A$5:$A$180,$C$3,'Cost Report'!$B$5:$B$180,$B22) -> 0 | Q22: =SUMIFS('Cost Report'!$Q$5:$Q$180,'Cost Report'!$A$5:$A$180,$C$3,'Cost Report'!$B$5:$B$180,$B22) -> 0 | R22: =SUMIFS('Cost Report'!$R$5:$R$180,'Cost Report'!$A$5:$A$180,$C$3,'Cost Report'!$B$5:$B$180,$B22) -> 0
B23: 08-100 | C23: =INDEX(Data_CostCodes!$B:$B,MATCH($B23,Data_CostCodes!$A:$A,0)) -> Doors, Frames & Hardware | D23: =INDEX(Data_CostCodes!$D:$D,MATCH($B23,Data_CostCodes!$A:$A,0)) -> Material | E23: =SUMIFS('Cost Report'!$E$5:$E$180,'Cost Report'!$A$5:$A$180,$C$3,'Cost Report'!$B$5:$B$180,$B23) -> 438400 | F23: =SUMIFS('Cost Report'!$F$5:$F$180,'Cost Report'!$A$5:$A$180,$C$3,'Cost Report'!$B$5:$B$180,$B23) -> 0 | G23: =SUMIFS('Cost Report'!$G$5:$G$180,'Cost Report'!$A$5:$A$180,$C$3,'Cost Report'!$B$5:$B$180,$B23) -> 438400 | H23: =SUMIFS('Cost Report'!$H$5:$H$180,'Cost Report'!$A$5:$A$180,$C$3,'Cost Report'!$B$5:$B$180,$B23) -> 46792.64 | I23: =SUMIFS('Cost Report'!$I$5:$I$180,'Cost Report'!$A$5:$A$180,$C$3,'Cost Report'!$B$5:$B$180,$B23) -> 430700 | J23: =IF(G23>0,K23/G23,0) -> 0.11 | K23: =SUMIFS('Cost Report'!$K$5:$K$180,'Cost Report'!$A$5:$A$180,$C$3,'Cost Report'!$B$5:$B$180,$B23) -> 48224 | L23: =IF(H23>0,K23/H23,"") -> 1.0305894 | M23: =SUMIFS('Cost Report'!$M$5:$M$180,'Cost Report'!$A$5:$A$180,$C$3,'Cost Report'!$B$5:$B$180,$B23) -> 430700 | N23: =SUMIFS('Cost Report'!$N$5:$N$180,'Cost Report'!$A$5:$A$180,$C$3,'Cost Report'!$B$5:$B$180,$B23) -> 7700 | O23: =SUMIFS('Cost Report'!$O$5:$O$180,'Cost Report'!$A$5:$A$180,$C$3,'Cost Report'!$B$5:$B$180,$B23) -> 383907.36 | P23: =SUMIFS('Cost Report'!$P$5:$P$180,'Cost Report'!$A$5:$A$180,$C$3,'Cost Report'!$B$5:$B$180,$B23) -> 0 | Q23: =SUMIFS('Cost Report'!$Q$5:$Q$180,'Cost Report'!$A$5:$A$180,$C$3,'Cost Report'!$B$5:$B$180,$B23) -> 0 | R23: =SUMIFS('Cost Report'!$R$5:$R$180,'Cost Report'!$A$5:$A$180,$C$3,'Cost Report'!$B$5:$B$180,$B23) -> 0
... B26: 16-000 | C26: =INDEX(Data_CostCodes!$B:$B,MATCH($B26,Data_CostCodes!$A:$A,0)) -> Electrical | D26: =INDEX(Data_CostCodes!$D:$D,MATCH($B26,Data_CostCodes!$A:$A,0)) -> Subcontract | E26: =SUMIFS('Cost Report'!$E$5:$E$180,'Cost Report'!$A$5:$A$180,$C$3,'Cost Report'!$B$5:$B$180,$B26) -> 1065000 | F26: =SUMIFS('Cost Report'!$F$5:$F$180,'Cost Report'!$A$5:$A$180,$C$3,'Cost Report'!$B$5:$B$180,$B26) -> 0 | G26: =SUMIFS('Cost Report'!$G$5:$G$180,'Cost Report'!$A$5:$A$180,$C$3,'Cost Report'!$B$5:$B$180,$B26) -> 1065000 | H26: =SUMIFS('Cost Report'!$H$5:$H$180,'Cost Report'!$A$5:$A$180,$C$3,'Cost Report'!$B$5:$B$180,$B26) -> 608567.8 | I26: =SUMIFS('Cost Report'!$I$5:$I$180,'Cost Report'!$A$5:$A$180,$C$3,'Cost Report'!$B$5:$B$180,$B26) -> 1052300 | J26: =IF(G26>0,K26/G26,0) -> 0.587 | K26: =SUMIFS('Cost Report'!$K$5:$K$180,'Cost Report'!$A$5:$A$180,$C$3,'Cost Report'!$B$5:$B$180,$B26) -> 625155 | L26: =IF(H26>0,K26/H26,"") -> 1.0272561 | M26: =SUMIFS('Cost Report'!$M$5:$M$180,'Cost Report'!$A$5:$A$180,$C$3,'Cost Report'!$B$5:$B$180,$B26) -> 1052300 | N26: =SUMIFS('Cost Report'!$N$5:$N$180,'Cost Report'!$A$5:$A$180,$C$3,'Cost Report'!$B$5:$B$180,$B26) -> 12700 | O26: =SUMIFS('Cost Report'!$O$5:$O$180,'Cost Report'!$A$5:$A$180,$C$3,'Cost Report'!$B$5:$B$180,$B26) -> 443732.2 | P26: =SUMIFS('Cost Report'!$P$5:$P$180,'Cost Report'!$A$5:$A$180,$C$3,'Cost Report'!$B$5:$B$180,$B26) -> 0 | Q26: =SUMIFS('Cost Report'!$Q$5:$Q$180,'Cost Report'!$A$5:$A$180,$C$3,'Cost Report'!$B$5:$B$180,$B26) -> 0 | R26: =SUMIFS('Cost Report'!$R$5:$R$180,'Cost Report'!$A$5:$A$180,$C$3,'Cost Report'!$B$5:$B$180,$B26) -> 0
B27: Job total | E27: =SUM(E12:E26) -> 10113400 | F27: =SUM(F12:F26) -> 650200 | G27: =SUM(G12:G26) -> 10763600 | H27: =SUM(H12:H26) -> 8582224.5 | I27: =SUM(I12:I26) -> 8139000 | J27: =IF(G27>0,K27/G27,0) -> 0.75182787 | K27: =SUM(K12:K26) -> 8092374.5 | L27: =IF(H27>0,K27/H27,0) -> 0.94292272 | M27: =SUM(M12:M26) -> 11519732 | N27: =SUM(N12:N26) -> -756132.28 | O27: =SUM(O12:O26) -> 2937507.8 | P27: =SUM(P12:P26) -> 30638 | Q27: =SUM(Q12:Q26) -> 30024.3 | R27: =SUM(R12:R26) -> 26817.041
B29: Cost codes not used on the selected job show as '-'. Red: forecast overrun above $25,000 or CPI below 0.95.

Sheet Monthly Cost
A1: Monthly Job Cost
A2: Posted cost by fiscal period from the job cost ledger (Data_JobCost).
A4: Period | B4: 23-098 | C4: 24-101 | D4: 24-104 | E4: 24-107 | F4: 25-110 | G4: 25-112 | H4: 25-115 | I4: 25-118 | J4: 25-121 | K4: 26-124 | L4: 26-127 | M4: 26-130 | N4: Portfolio | O4: Cumulative
A5: 202406 | B5: =SUMIFS(Data_JobCost!$L:$L,Data_JobCost!$C:$C,$A5,Data_JobCost!$D:$D,B$4) -> 39201.02 | C5: =SUMIFS(Data_JobCost!$L:$L,Data_JobCost!$C:$C,$A5,Data_JobCost!$D:$D,C$4) -> 0 | D5: =SUMIFS(Data_JobCost!$L:$L,Data_JobCost!$C:$C,$A5,Data_JobCost!$D:$D,D$4) -> 0 | E5: =SUMIFS(Data_JobCost!$L:$L,Data_JobCost!$C:$C,$A5,Data_JobCost!$D:$D,E$4) -> 0 | F5: =SUMIFS(Data_JobCost!$L:$L,Data_JobCost!$C:$C,$A5,Data_JobCost!$D:$D,F$4) -> 0 | G5: =SUMIFS(Data_JobCost!$L:$L,Data_JobCost!$C:$C,$A5,Data_JobCost!$D:$D,G$4) -> 0 | H5: =SUMIFS(Data_JobCost!$L:$L,Data_JobCost!$C:$C,$A5,Data_JobCost!$D:$D,H$4) -> 0 | I5: =SUMIFS(Data_JobCost!$L:$L,Data_JobCost!$C:$C,$A5,Data_JobCost!$D:$D,I$4) -> 0 | ... M5: =SUMIFS(Data_JobCost!$L:$L,Data_JobCost!$C:$C,$A5,Data_JobCost!$D:$D,M$4) -> 0 | N5: =SUM(B5:M5) -> 39201.02 | O5: =N5 -> 39201.02
A6: 202407 | B6: =SUMIFS(Data_JobCost!$L:$L,Data_JobCost!$C:$C,$A6,Data_JobCost!$D:$D,B$4) -> 91276.61 | C6: =SUMIFS(Data_JobCost!$L:$L,Data_JobCost!$C:$C,$A6,Data_JobCost!$D:$D,C$4) -> 0 | D6: =SUMIFS(Data_JobCost!$L:$L,Data_JobCost!$C:$C,$A6,Data_JobCost!$D:$D,D$4) -> 0 | E6: =SUMIFS(Data_JobCost!$L:$L,Data_JobCost!$C:$C,$A6,Data_JobCost!$D:$D,E$4) -> 0 | F6: =SUMIFS(Data_JobCost!$L:$L,Data_JobCost!$C:$C,$A6,Data_JobCost!$D:$D,F$4) -> 0 | G6: =SUMIFS(Data_JobCost!$L:$L,Data_JobCost!$C:$C,$A6,Data_JobCost!$D:$D,G$4) -> 0 | H6: =SUMIFS(Data_JobCost!$L:$L,Data_JobCost!$C:$C,$A6,Data_JobCost!$D:$D,H$4) -> 0 | I6: =SUMIFS(Data_JobCost!$L:$L,Data_JobCost!$C:$C,$A6,Data_JobCost!$D:$D,I$4) -> 0 | ... M6: =SUMIFS(Data_JobCost!$L:$L,Data_JobCost!$C:$C,$A6,Data_JobCost!$D:$D,M$4) -> 0 | N6: =SUM(B6:M6) -> 91276.61 | O6: =O5+N6 -> 130477.63
A7: 202408 | B7: =SUMIFS(Data_JobCost!$L:$L,Data_JobCost!$C:$C,$A7,Data_JobCost!$D:$D,B$4) -> 184236.51 | C7: =SUMIFS(Data_JobCost!$L:$L,Data_JobCost!$C:$C,$A7,Data_JobCost!$D:$D,C$4) -> 0 | D7: =SUMIFS(Data_JobCost!$L:$L,Data_JobCost!$C:$C,$A7,Data_JobCost!$D:$D,D$4) -> 0 | E7: =SUMIFS(Data_JobCost!$L:$L,Data_JobCost!$C:$C,$A7,Data_JobCost!$D:$D,E$4) -> 0 | F7: =SUMIFS(Data_JobCost!$L:$L,Data_JobCost!$C:$C,$A7,Data_JobCost!$D:$D,F$4) -> 0 | G7: =SUMIFS(Data_JobCost!$L:$L,Data_JobCost!$C:$C,$A7,Data_JobCost!$D:$D,G$4) -> 0 | H7: =SUMIFS(Data_JobCost!$L:$L,Data_JobCost!$C:$C,$A7,Data_JobCost!$D:$D,H$4) -> 0 | I7: =SUMIFS(Data_JobCost!$L:$L,Data_JobCost!$C:$C,$A7,Data_JobCost!$D:$D,I$4) -> 0 | ... M7: =SUMIFS(Data_JobCost!$L:$L,Data_JobCost!$C:$C,$A7,Data_JobCost!$D:$D,M$4) -> 0 | N7: =SUM(B7:M7) -> 184236.51 | O7: =O6+N7 -> 314714.14
A8: 202409 | B8: =SUMIFS(Data_JobCost!$L:$L,Data_JobCost!$C:$C,$A8,Data_JobCost!$D:$D,B$4) -> 245464.58 | C8: =SUMIFS(Data_JobCost!$L:$L,Data_JobCost!$C:$C,$A8,Data_JobCost!$D:$D,C$4) -> 0 | D8: =SUMIFS(Data_JobCost!$L:$L,Data_JobCost!$C:$C,$A8,Data_JobCost!$D:$D,D$4) -> 0 | E8: =SUMIFS(Data_JobCost!$L:$L,Data_JobCost!$C:$C,$A8,Data_JobCost!$D:$D,E$4) -> 0 | F8: =SUMIFS(Data_JobCost!$L:$L,Data_JobCost!$C:$C,$A8,Data_JobCost!$D:$D,F$4) -> 0 | G8: =SUMIFS(Data_JobCost!$L:$L,Data_JobCost!$C:$C,$A8,Data_JobCost!$D:$D,G$4) -> 0 | H8: =SUMIFS(Data_JobCost!$L:$L,Data_JobCost!$C:$C,$A8,Data_JobCost!$D:$D,H$4) -> 0 | I8: =SUMIFS(Data_JobCost!$L:$L,Data_JobCost!$C:$C,$A8,Data_JobCost!$D:$D,I$4) -> 0 | ... M8: =SUMIFS(Data_JobCost!$L:$L,Data_JobCost!$C:$C,$A8,Data_JobCost!$D:$D,M$4) -> 0 | N8: =SUM(B8:M8) -> 245464.58 | O8: =O7+N8 -> 560178.72
A9: 202410 | B9: =SUMIFS(Data_JobCost!$L:$L,Data_JobCost!$C:$C,$A9,Data_JobCost!$D:$D,B$4) -> 342893.6 | C9: =SUMIFS(Data_JobCost!$L:$L,Data_JobCost!$C:$C,$A9,Data_JobCost!$D:$D,C$4) -> 0 | D9: =SUMIFS(Data_JobCost!$L:$L,Data_JobCost!$C:$C,$A9,Data_JobCost!$D:$D,D$4) -> 0 | E9: =SUMIFS(Data_JobCost!$L:$L,Data_JobCost!$C:$C,$A9,Data_JobCost!$D:$D,E$4) -> 0 | F9: =SUMIFS(Data_JobCost!$L:$L,Data_JobCost!$C:$C,$A9,Data_JobCost!$D:$D,F$4) -> 0 | G9: =SUMIFS(Data_JobCost!$L:$L,Data_JobCost!$C:$C,$A9,Data_JobCost!$D:$D,G$4) -> 0 | H9: =SUMIFS(Data_JobCost!$L:$L,Data_JobCost!$C:$C,$A9,Data_JobCost!$D:$D,H$4) -> 0 | I9: =SUMIFS(Data_JobCost!$L:$L,Data_JobCost!$C:$C,$A9,Data_JobCost!$D:$D,I$4) -> 0 | ... M9: =SUMIFS(Data_JobCost!$L:$L,Data_JobCost!$C:$C,$A9,Data_JobCost!$D:$D,M$4) -> 0 | N9: =SUM(B9:M9) -> 342893.6 | O9: =O8+N9 -> 903072.32
A10: 202411 | B10: =SUMIFS(Data_JobCost!$L:$L,Data_JobCost!$C:$C,$A10,Data_JobCost!$D:$D,B$4) -> 384273.5 | C10: =SUMIFS(Data_JobCost!$L:$L,Data_JobCost!$C:$C,$A10,Data_JobCost!$D:$D,C$4) -> 0 | D10: =SUMIFS(Data_JobCost!$L:$L,Data_JobCost!$C:$C,$A10,Data_JobCost!$D:$D,D$4) -> 0 | E10: =SUMIFS(Data_JobCost!$L:$L,Data_JobCost!$C:$C,$A10,Data_JobCost!$D:$D,E$4) -> 0 | F10: =SUMIFS(Data_JobCost!$L:$L,Data_JobCost!$C:$C,$A10,Data_JobCost!$D:$D,F$4) -> 0 | G10: =SUMIFS(Data_JobCost!$L:$L,Data_JobCost!$C:$C,$A10,Data_JobCost!$D:$D,G$4) -> 0 | H10: =SUMIFS(Data_JobCost!$L:$L,Data_JobCost!$C:$C,$A10,Data_JobCost!$D:$D,H$4) -> 0 | I10: =SUMIFS(Data_JobCost!$L:$L,Data_JobCost!$C:$C,$A10,Data_JobCost!$D:$D,I$4) -> 0 | ... M10: =SUMIFS(Data_JobCost!$L:$L,Data_JobCost!$C:$C,$A10,Data_JobCost!$D:$D,M$4) -> 0 | N10: =SUM(B10:M10) -> 384273.5 | O10: =O9+N10 -> 1287345.8
A11: 202412 | B11: =SUMIFS(Data_JobCost!$L:$L,Data_JobCost!$C:$C,$A11,Data_JobCost!$D:$D,B$4) -> 438101.97 | C11: =SUMIFS(Data_JobCost!$L:$L,Data_JobCost!$C:$C,$A11,Data_JobCost!$D:$D,C$4) -> 0 | D11: =SUMIFS(Data_JobCost!$L:$L,Data_JobCost!$C:$C,$A11,Data_JobCost!$D:$D,D$4) -> 0 | E11: =SUMIFS(Data_JobCost!$L:$L,Data_JobCost!$C:$C,$A11,Data_JobCost!$D:$D,E$4) -> 0 | F11: =SUMIFS(Data_JobCost!$L:$L,Data_JobCost!$C:$C,$A11,Data_JobCost!$D:$D,F$4) -> 0 | G11: =SUMIFS(Data_JobCost!$L:$L,Data_JobCost!$C:$C,$A11,Data_JobCost!$D:$D,G$4) -> 0 | H11: =SUMIFS(Data_JobCost!$L:$L,Data_JobCost!$C:$C,$A11,Data_JobCost!$D:$D,H$4) -> 0 | I11: =SUMIFS(Data_JobCost!$L:$L,Data_JobCost!$C:$C,$A11,Data_JobCost!$D:$D,I$4) -> 0 | ... M11: =SUMIFS(Data_JobCost!$L:$L,Data_JobCost!$C:$C,$A11,Data_JobCost!$D:$D,M$4) -> 0 | N11: =SUM(B11:M11) -> 438101.97 | O11: =O10+N11 -> 1725447.8
A12: 202501 | B12: =SUMIFS(Data_JobCost!$L:$L,Data_JobCost!$C:$C,$A12,Data_JobCost!$D:$D,B$4) -> 558702.16 | C12: =SUMIFS(Data_JobCost!$L:$L,Data_JobCost!$C:$C,$A12,Data_JobCost!$D:$D,C$4) -> 0 | D12: =SUMIFS(Data_JobCost!$L:$L,Data_JobCost!$C:$C,$A12,Data_JobCost!$D:$D,D$4) -> 0 | E12: =SUMIFS(Data_JobCost!$L:$L,Data_JobCost!$C:$C,$A12,Data_JobCost!$D:$D,E$4) -> 0 | F12: =SUMIFS(Data_JobCost!$L:$L,Data_JobCost!$C:$C,$A12,Data_JobCost!$D:$D,F$4) -> 0 | G12: =SUMIFS(Data_JobCost!$L:$L,Data_JobCost!$C:$C,$A12,Data_JobCost!$D:$D,G$4) -> 0 | H12: =SUMIFS(Data_JobCost!$L:$L,Data_JobCost!$C:$C,$A12,Data_JobCost!$D:$D,H$4) -> 0 | I12: =SUMIFS(Data_JobCost!$L:$L,Data_JobCost!$C:$C,$A12,Data_JobCost!$D:$D,I$4) -> 0 | ... M12: =SUMIFS(Data_JobCost!$L:$L,Data_JobCost!$C:$C,$A12,Data_JobCost!$D:$D,M$4) -> 0 | N12: =SUM(B12:M12) -> 558702.16 | O12: =O11+N12 -> 2284150
A13: 202502 | B13: =SUMIFS(Data_JobCost!$L:$L,Data_JobCost!$C:$C,$A13,Data_JobCost!$D:$D,B$4) -> 520964.18 | C13: =SUMIFS(Data_JobCost!$L:$L,Data_JobCost!$C:$C,$A13,Data_JobCost!$D:$D,C$4) -> 0 | D13: =SUMIFS(Data_JobCost!$L:$L,Data_JobCost!$C:$C,$A13,Data_JobCost!$D:$D,D$4) -> 0 | E13: =SUMIFS(Data_JobCost!$L:$L,Data_JobCost!$C:$C,$A13,Data_JobCost!$D:$D,E$4) -> 0 | F13: =SUMIFS(Data_JobCost!$L:$L,Data_JobCost!$C:$C,$A13,Data_JobCost!$D:$D,F$4) -> 0 | G13: =SUMIFS(Data_JobCost!$L:$L,Data_JobCost!$C:$C,$A13,Data_JobCost!$D:$D,G$4) -> 0 | H13: =SUMIFS(Data_JobCost!$L:$L,Data_JobCost!$C:$C,$A13,Data_JobCost!$D:$D,H$4) -> 0 | I13: =SUMIFS(Data_JobCost!$L:$L,Data_JobCost!$C:$C,$A13,Data_JobCost!$D:$D,I$4) -> 0 | ... M13: =SUMIFS(Data_JobCost!$L:$L,Data_JobCost!$C:$C,$A13,Data_JobCost!$D:$D,M$4) -> 0 | N13: =SUM(B13:M13) -> 520964.18 | O13: =O12+N13 -> 2805114.1
A14: 202503 | B14: =SUMIFS(Data_JobCost!$L:$L,Data_JobCost!$C:$C,$A14,Data_JobCost!$D:$D,B$4) -> 667866.28 | C14: =SUMIFS(Data_JobCost!$L:$L,Data_JobCost!$C:$C,$A14,Data_JobCost!$D:$D,C$4) -> 141082.97 | D14: =SUMIFS(Data_JobCost!$L:$L,Data_JobCost!$C:$C,$A14,Data_JobCost!$D:$D,D$4) -> 0 | E14: =SUMIFS(Data_JobCost!$L:$L,Data_JobCost!$C:$C,$A14,Data_JobCost!$D:$D,E$4) -> 0 | F14: =SUMIFS(Data_JobCost!$L:$L,Data_JobCost!$C:$C,$A14,Data_JobCost!$D:$D,F$4) -> 0 | G14: =SUMIFS(Data_JobCost!$L:$L,Data_JobCost!$C:$C,$A14,Data_JobCost!$D:$D,G$4) -> 0 | H14: =SUMIFS(Data_JobCost!$L:$L,Data_JobCost!$C:$C,$A14,Data_JobCost!$D:$D,H$4) -> 0 | I14: =SUMIFS(Data_JobCost!$L:$L,Data_JobCost!$C:$C,$A14,Data_JobCost!$D:$D,I$4) -> 0 | ... M14: =SUMIFS(Data_JobCost!$L:$L,Data_JobCost!$C:$C,$A14,Data_JobCost!$D:$D,M$4) -> 0 | N14: =SUM(B14:M14) -> 808949.25 | O14: =O13+N14 -> 3614063.4
A15: 202504 | B15: =SUMIFS(Data_JobCost!$L:$L,Data_JobCost!$C:$C,$A15,Data_JobCost!$D:$D,B$4) -> 701693.98 | C15: =SUMIFS(Data_JobCost!$L:$L,Data_JobCost!$C:$C,$A15,Data_JobCost!$D:$D,C$4) -> 375657.23 | D15: =SUMIFS(Data_JobCost!$L:$L,Data_JobCost!$C:$C,$A15,Data_JobCost!$D:$D,D$4) -> 0 | E15: =SUMIFS(Data_JobCost!$L:$L,Data_JobCost!$C:$C,$A15,Data_JobCost!$D:$D,E$4) -> 0 | F15: =SUMIFS(Data_JobCost!$L:$L,Data_JobCost!$C:$C,$A15,Data_JobCost!$D:$D,F$4) -> 0 | G15: =SUMIFS(Data_JobCost!$L:$L,Data_JobCost!$C:$C,$A15,Data_JobCost!$D:$D,G$4) -> 0 | H15: =SUMIFS(Data_JobCost!$L:$L,Data_JobCost!$C:$C,$A15,Data_JobCost!$D:$D,H$4) -> 0 | I15: =SUMIFS(Data_JobCost!$L:$L,Data_JobCost!$C:$C,$A15,Data_JobCost!$D:$D,I$4) -> 0 | ... M15: =SUMIFS(Data_JobCost!$L:$L,Data_JobCost!$C:$C,$A15,Data_JobCost!$D:$D,M$4) -> 0 | N15: =SUM(B15:M15) -> 1077351.2 | O15: =O14+N15 -> 4691414.6
A16: 202505 | B16: =SUMIFS(Data_JobCost!$L:$L,Data_JobCost!$C:$C,$A16,Data_JobCost!$D:$D,B$4) -> 744704.94 | C16: =SUMIFS(Data_JobCost!$L:$L,Data_JobCost!$C:$C,$A16,Data_JobCost!$D:$D,C$4) -> 805086.61 | D16: =SUMIFS(Data_JobCost!$L:$L,Data_JobCost!$C:$C,$A16,Data_JobCost!$D:$D,D$4) -> 66021.25 | E16: =SUMIFS(Data_JobCost!$L:$L,Data_JobCost!$C:$C,$A16,Data_JobCost!$D:$D,E$4) -> 0 | F16: =SUMIFS(Data_JobCost!$L:$L,Data_JobCost!$C:$C,$A16,Data_JobCost!$D:$D,F$4) -> 0 | G16: =SUMIFS(Data_JobCost!$L:$L,Data_JobCost!$C:$C,$A16,Data_JobCost!$D:$D,G$4) -> 0 | H16: =SUMIFS(Data_JobCost!$L:$L,Data_JobCost!$C:$C,$A16,Data_JobCost!$D:$D,H$4) -> 0 | I16: =SUMIFS(Data_JobCost!$L:$L,Data_JobCost!$C:$C,$A16,Data_JobCost!$D:$D,I$4) -> 0 | ... M16: =SUMIFS(Data_JobCost!$L:$L,Data_JobCost!$C:$C,$A16,Data_JobCost!$D:$D,M$4) -> 0 | N16: =SUM(B16:M16) -> 1615812.8 | O16: =O15+N16 -> 6307227.4
A17: 202506 | B17: =SUMIFS(Data_JobCost!$L:$L,Data_JobCost!$C:$C,$A17,Data_JobCost!$D:$D,B$4) -> 726320.95 | C17: =SUMIFS(Data_JobCost!$L:$L,Data_JobCost!$C:$C,$A17,Data_JobCost!$D:$D,C$4) -> 878383.12 | D17: =SUMIFS(Data_JobCost!$L:$L,Data_JobCost!$C:$C,$A17,Data_JobCost!$D:$D,D$4) -> 164577.98 | E17: =SUMIFS(Data_JobCost!$L:$L,Data_JobCost!$C:$C,$A17,Data_JobCost!$D:$D,E$4) -> 99896.84 | F17: =SUMIFS(Data_JobCost!$L:$L,Data_JobCost!$C:$C,$A17,Data_JobCost!$D:$D,F$4) -> 0 | G17: =SUMIFS(Data_JobCost!$L:$L,Data_JobCost!$C:$C,$A17,Data_JobCost!$D:$D,G$4) -> 0 | H17: =SUMIFS(Data_JobCost!$L:$L,Data_JobCost!$C:$C,$A17,Data_JobCost!$D:$D,H$4) -> 0 | I17: =SUMIFS(Data_JobCost!$L:$L,Data_JobCost!$C:$C,$A17,Data_JobCost!$D:$D,I$4) -> 0 | ... M17: =SUMIFS(Data_JobCost!$L:$L,Data_JobCost!$C:$C,$A17,Data_JobCost!$D:$D,M$4) -> 0 | N17: =SUM(B17:M17) -> 1869178.9 | O17: =O16+N17 -> 8176406.3
... A32: 202609 | B32: =SUMIFS(Data_JobCost!$L:$L,Data_JobCost!$C:$C,$A32,Data_JobCost!$D:$D,B$4) -> 0.08 | C32: =SUMIFS(Data_JobCost!$L:$L,Data_JobCost!$C:$C,$A32,Data_JobCost!$D:$D,C$4) -> 468436.37 | D32: =SUMIFS(Data_JobCost!$L:$L,Data_JobCost!$C:$C,$A32,Data_JobCost!$D:$D,D$4) -> 930111.3 | E32: =SUMIFS(Data_JobCost!$L:$L,Data_JobCost!$C:$C,$A32,Data_JobCost!$D:$D,E$4) -> 139144.77 | F32: =SUMIFS(Data_JobCost!$L:$L,Data_JobCost!$C:$C,$A32,Data_JobCost!$D:$D,F$4) -> 1671920.1 | G32: =SUMIFS(Data_JobCost!$L:$L,Data_JobCost!$C:$C,$A32,Data_JobCost!$D:$D,G$4) -> 501877.2 | H32: =SUMIFS(Data_JobCost!$L:$L,Data_JobCost!$C:$C,$A32,Data_JobCost!$D:$D,H$4) -> 949845.75 | I32: =SUMIFS(Data_JobCost!$L:$L,Data_JobCost!$C:$C,$A32,Data_JobCost!$D:$D,I$4) -> 1288492 | ... M32: =SUMIFS(Data_JobCost!$L:$L,Data_JobCost!$C:$C,$A32,Data_JobCost!$D:$D,M$4) -> 299631.7 | N32: =SUM(B32:M32) -> 9147415.3 | O32: =O31+N32 -> 1.1457826e+08
A33: Total | B33: =SUM(B5:B32) -> 14275865 | C33: =SUM(C5:C32) -> 19031041 | D33: =SUM(D5:D32) -> 13766951 | E33: =SUM(E5:E32) -> 8639590.5 | F33: =SUM(F5:F32) -> 15913660 | G33: =SUM(G5:G32) -> 7797690.6 | H33: =SUM(H5:H32) -> 8582224.5 | I33: =SUM(I5:I32) -> 13092124 | ... N33: =SUM(N5:N32) -> 1.1457826e+08

Sheet Cost Report
A1: Cost Report — cost-code level (feeds WIP Schedule and Job Detail)
A2: One row per budget line in the ERP export. Every value is a formula on the Data_ tabs.
A4: Job No | B4: Cost Code | C4: Description | D4: Cost Type | E4: Original Budget | F4: Budget Changes | G4: Revised Budget | H4: Actual Cost | I4: Committed | J4: % Complete | K4: Earned Value | L4: CPI | M4: Forecast Cost (EAC) | N4: Variance at Completion | O4: Cost to Complete | P4: Budget Hours | Q4: Actual Hours | R4: Earned Hours
A5: 23-098 | B5: 01-100 | C5: =INDEX(Data_CostCodes!$B:$B,MATCH($B5,Data_CostCodes!$A:$A,0)) -> General Conditions - Supervision | D5: =INDEX(Data_CostCodes!$D:$D,MATCH($B5,Data_CostCodes!$A:$A,0)) -> Labour | E5: =SUMIFS(Data_Budgets!$C:$C,Data_Budgets!$A:$A,$A5,Data_Budgets!$B:$B,$B5) -> 1055600 | F5: =SUMIFS(Data_Budgets!$D:$D,Data_Budgets!$A:$A,$A5,Data_Budgets!$B:$B,$B5) -> 0 | G5: =E5+F5 -> 1055600 | H5: =SUMIFS(Data_JobCost!$L:$L,Data_JobCost!$D:$D,$A5,Data_JobCost!$E:$E,$B5) -> 1056376.1 | I5: =SUMIFS(Data_Commitments!$E:$E,Data_Commitments!$B:$B,$A5,Data_Commitments!$C:$C,$B5) -> 0 | J5: =SUMIFS(Data_Progress!$C:$C,Data_Progress!$A:$A,$A5,Data_Progress!$B:$B,$B5) -> 0.98 | K5: =G5*J5 -> 1034488 | L5: =IF(H5>0,K5/H5,"") -> 0.97928003 | M5: =IF(I5>0,MAX(I5,H5),IF(J5>0,H5+(G5-K5)/L5,G5)) -> 1077934.8 | N5: =G5-M5 -> -22334.776 | O5: =M5-H5 -> 21558.696 | P5: =SUMIFS(Data_Budgets!$F:$F,Data_Budgets!$A:$A,$A5,Data_Budgets!$B:$B,$B5) -> 11474 | Q5: =SUMIFS(Data_JobCost!$K:$K,Data_JobCost!$D:$D,$A5,Data_JobCost!$E:$E,$B5) -> 11482.4 | R5: =P5*J5 -> 11244.52
A6: 23-098 | B6: 01-200 | C6: =INDEX(Data_CostCodes!$B:$B,MATCH($B6,Data_CostCodes!$A:$A,0)) -> Site Facilities & Temp Services | D6: =INDEX(Data_CostCodes!$D:$D,MATCH($B6,Data_CostCodes!$A:$A,0)) -> Other | E6: =SUMIFS(Data_Budgets!$C:$C,Data_Budgets!$A:$A,$A6,Data_Budgets!$B:$B,$B6) -> 405700 | F6: =SUMIFS(Data_Budgets!$D:$D,Data_Budgets!$A:$A,$A6,Data_Budgets!$B:$B,$B6) -> 0 | G6: =E6+F6 -> 405700 | H6: =SUMIFS(Data_JobCost!$L:$L,Data_JobCost!$D:$D,$A6,Data_JobCost!$E:$E,$B6) -> 411510.56 | I6: =SUMIFS(Data_Commitments!$E:$E,Data_Commitments!$B:$B,$A6,Data_Commitments!$C:$C,$B6) -> 0 | J6: =SUMIFS(Data_Progress!$C:$C,Data_Progress!$A:$A,$A6,Data_Progress!$B:$B,$B6) -> 1 | K6: =G6*J6 -> 405700 | L6: =IF(H6>0,K6/H6,"") -> 0.98587992 | M6: =IF(I6>0,MAX(I6,H6),IF(J6>0,H6+(G6-K6)/L6,G6)) -> 411510.56 | N6: =G6-M6 -> -5810.56 | O6: =M6-H6 -> 0 | P6: =SUMIFS(Data_Budgets!$F:$F,Data_Budgets!$A:$A,$A6,Data_Budgets!$B:$B,$B6) -> 0 | Q6: =SUMIFS(Data_JobCost!$K:$K,Data_JobCost!$D:$D,$A6,Data_JobCost!$E:$E,$B6) -> 0 | R6: =P6*J6 -> 0
A7: 23-098 | B7: 01-500 | C7: =INDEX(Data_CostCodes!$B:$B,MATCH($B7,Data_CostCodes!$A:$A,0)) -> Equipment Rental | D7: =INDEX(Data_CostCodes!$D:$D,MATCH($B7,Data_CostCodes!$A:$A,0)) -> Equipment | E7: =SUMIFS(Data_Budgets!$C:$C,Data_Budgets!$A:$A,$A7,Data_Budgets!$B:$B,$B7) -> 385500 | F7: =SUMIFS(Data_Budgets!$D:$D,Data_Budgets!$A:$A,$A7,Data_Budgets!$B:$B,$B7) -> 0 | G7: =E7+F7 -> 385500 | H7: =SUMIFS(Data_JobCost!$L:$L,Data_JobCost!$D:$D,$A7,Data_JobCost!$E:$E,$B7) -> 398775.35 | I7: =SUMIFS(Data_Commitments!$E:$E,Data_Commitments!$B:$B,$A7,Data_Commitments!$C:$C,$B7) -> 0 | J7: =SUMIFS(Data_Progress!$C:$C,Data_Progress!$A:$A,$A7,Data_Progress!$B:$B,$B7) -> 1 | K7: =G7*J7 -> 385500 | L7: =IF(H7>0,K7/H7,"") -> 0.9667097 | M7: =IF(I7>0,MAX(I7,H7),IF(J7>0,H7+(G7-K7)/L7,G7)) -> 398775.35 | N7: =G7-M7 -> -13275.35 | O7: =M7-H7 -> 0 | P7: =SUMIFS(Data_Budgets!$F:$F,Data_Budgets!$A:$A,$A7,Data_Budgets!$B:$B,$B7) -> 0 | Q7: =SUMIFS(Data_JobCost!$K:$K,Data_JobCost!$D:$D,$A7,Data_JobCost!$E:$E,$B7) -> 0 | R7: =P7*J7 -> 0
A8: 23-098 | B8: 02-200 | C8: =INDEX(Data_CostCodes!$B:$B,MATCH($B8,Data_CostCodes!$A:$A,0)) -> Earthwork & Excavation | D8: =INDEX(Data_CostCodes!$D:$D,MATCH($B8,Data_CostCodes!$A:$A,0)) -> Subcontract | E8: =SUMIFS(Data_Budgets!$C:$C,Data_Budgets!$A:$A,$A8,Data_Budgets!$B:$B,$B8) -> 499000 | F8: =SUMIFS(Data_Budgets!$D:$D,Data_Budgets!$A:$A,$A8,Data_Budgets!$B:$B,$B8) -> 0 | G8: =E8+F8 -> 499000 | H8: =SUMIFS(Data_JobCost!$L:$L,Data_JobCost!$D:$D,$A8,Data_JobCost!$E:$E,$B8) -> 498175.49 | I8: =SUMIFS(Data_Commitments!$E:$E,Data_Commitments!$B:$B,$A8,Data_Commitments!$C:$C,$B8) -> 504300 | J8: =SUMIFS(Data_Progress!$C:$C,Data_Progress!$A:$A,$A8,Data_Progress!$B:$B,$B8) -> 1 | K8: =G8*J8 -> 499000 | L8: =IF(H8>0,K8/H8,"") -> 1.0016551 | M8: =IF(I8>0,MAX(I8,H8),IF(J8>0,H8+(G8-K8)/L8,G8)) -> 504300 | N8: =G8-M8 -> -5300 | O8: =M8-H8 -> 6124.51 | P8: =SUMIFS(Data_Budgets!$F:$F,Data_Budgets!$A:$A,$A8,Data_Budgets!$B:$B,$B8) -> 0 | Q8: =SUMIFS(Data_JobCost!$K:$K,Data_JobCost!$D:$D,$A8,Data_JobCost!$E:$E,$B8) -> 0 | R8: =P8*J8 -> 0
A9: 23-098 | B9: 03-100 | C9: =INDEX(Data_CostCodes!$B:$B,MATCH($B9,Data_CostCodes!$A:$A,0)) -> Concrete Formwork | D9: =INDEX(Data_CostCodes!$D:$D,MATCH($B9,Data_CostCodes!$A:$A,0)) -> Labour | E9: =SUMIFS(Data_Budgets!$C:$C,Data_Budgets!$A:$A,$A9,Data_Budgets!$B:$B,$B9) -> 620700 | F9: =SUMIFS(Data_Budgets!$D:$D,Data_Budgets!$A:$A,$A9,Data_Budgets!$B:$B,$B9) -> 0 | G9: =E9+F9 -> 620700 | H9: =SUMIFS(Data_JobCost!$L:$L,Data_JobCost!$D:$D,$A9,Data_JobCost!$E:$E,$B9) -> 617156.55 | I9: =SUMIFS(Data_Commitments!$E:$E,Data_Commitments!$B:$B,$A9,Data_Commitments!$C:$C,$B9) -> 0 | J9: =SUMIFS(Data_Progress!$C:$C,Data_Progress!$A:$A,$A9,Data_Progress!$B:$B,$B9) -> 1 | K9: =G9*J9 -> 620700 | L9: =IF(H9>0,K9/H9,"") -> 1.0057416 | M9: =IF(I9>0,MAX(I9,H9),IF(J9>0,H9+(G9-K9)/L9,G9)) -> 617156.55 | N9: =G9-M9 -> 3543.45 | O9: =M9-H9 -> 0 | P9: =SUMIFS(Data_Budgets!$F:$F,Data_Budgets!$A:$A,$A9,Data_Budgets!$B:$B,$B9) -> 8388 | Q9: =SUMIFS(Data_JobCost!$K:$K,Data_JobCost!$D:$D,$A9,Data_JobCost!$E:$E,$B9) -> 8339.6 | R9: =P9*J9 -> 8388
A10: 23-098 | B10: 03-200 | C10: =INDEX(Data_CostCodes!$B:$B,MATCH($B10,Data_CostCodes!$A:$A,0)) -> Reinforcing Steel | D10: =INDEX(Data_CostCodes!$D:$D,MATCH($B10,Data_CostCodes!$A:$A,0)) -> Material | E10: =SUMIFS(Data_Budgets!$C:$C,Data_Budgets!$A:$A,$A10,Data_Budgets!$B:$B,$B10) -> 564400 | F10: =SUMIFS(Data_Budgets!$D:$D,Data_Budgets!$A:$A,$A10,Data_Budgets!$B:$B,$B10) -> 0 | G10: =E10+F10 -> 564400 | H10: =SUMIFS(Data_JobCost!$L:$L,Data_JobCost!$D:$D,$A10,Data_JobCost!$E:$E,$B10) -> 540645.37 | I10: =SUMIFS(Data_Commitments!$E:$E,Data_Commitments!$B:$B,$A10,Data_Commitments!$C:$C,$B10) -> 557000 | J10: =SUMIFS(Data_Progress!$C:$C,Data_Progress!$A:$A,$A10,Data_Progress!$B:$B,$B10) -> 1 | K10: =G10*J10 -> 564400 | L10: =IF(H10>0,K10/H10,"") -> 1.0439375 | M10: =IF(I10>0,MAX(I10,H10),IF(J10>0,H10+(G10-K10)/L10,G10)) -> 557000 | N10: =G10-M10 -> 7400 | O10: =M10-H10 -> 16354.63 | P10: =SUMIFS(Data_Budgets!$F:$F,Data_Budgets!$A:$A,$A10,Data_Budgets!$B:$B,$B10) -> 0 | Q10: =SUMIFS(Data_JobCost!$K:$K,Data_JobCost!$D:$D,$A10,Data_JobCost!$E:$E,$B10) -> 0 | R10: =P10*J10 -> 0
A11: 23-098 | B11: 03-300 | C11: =INDEX(Data_CostCodes!$B:$B,MATCH($B11,Data_CostCodes!$A:$A,0)) -> Cast-in-Place Concrete | D11: =INDEX(Data_CostCodes!$D:$D,MATCH($B11,Data_CostCodes!$A:$A,0)) -> Material | E11: =SUMIFS(Data_Budgets!$C:$C,Data_Budgets!$A:$A,$A11,Data_Budgets!$B:$B,$B11) -> 1018900 | F11: =SUMIFS(Data_Budgets!$D:$D,Data_Budgets!$A:$A,$A11,Data_Budgets!$B:$B,$B11) -> 0 | G11: =E11+F11 -> 1018900 | H11: =SUMIFS(Data_JobCost!$L:$L,Data_JobCost!$D:$D,$A11,Data_JobCost!$E:$E,$B11) -> 995639.07 | I11: =SUMIFS(Data_Commitments!$E:$E,Data_Commitments!$B:$B,$A11,Data_Commitments!$C:$C,$B11) -> 1000500 | J11: =SUMIFS(Data_Progress!$C:$C,Data_Progress!$A:$A,$A11,Data_Progress!$B:$B,$B11) -> 1 | K11: =G11*J11 -> 1018900 | L11: =IF(H11>0,K11/H11,"") -> 1.0233628 | M11: =IF(I11>0,MAX(I11,H11),IF(J11>0,H11+(G11-K11)/L11,G11)) -> 1000500 | N11: =G11-M11 -> 18400 | O11: =M11-H11 -> 4860.93 | P11: =SUMIFS(Data_Budgets!$F:$F,Data_Budgets!$A:$A,$A11,Data_Budgets!$B:$B,$B11) -> 0 | Q11: =SUMIFS(Data_JobCost!$K:$K,Data_JobCost!$D:$D,$A11,Data_JobCost!$E:$E,$B11) -> 0 | R11: =P11*J11 -> 0
A12: 23-098 | B12: 04-200 | C12: =INDEX(Data_CostCodes!$B:$B,MATCH($B12,Data_CostCodes!$A:$A,0)) -> Masonry | D12: =INDEX(Data_CostCodes!$D:$D,MATCH($B12,Data_CostCodes!$A:$A,0)) -> Subcontract | E12: =SUMIFS(Data_Budgets!$C:$C,Data_Budgets!$A:$A,$A12,Data_Budgets!$B:$B,$B12) -> 820600 | F12: =SUMIFS(Data_Budgets!$D:$D,Data_Budgets!$A:$A,$A12,Data_Budgets!$B:$B,$B12) -> 0 | G12: =E12+F12 -> 820600 | H12: =SUMIFS(Data_JobCost!$L:$L,Data_JobCost!$D:$D,$A12,Data_JobCost!$E:$E,$B12) -> 793421.31 | I12: =SUMIFS(Data_Commitments!$E:$E,Data_Commitments!$B:$B,$A12,Data_Commitments!$C:$C,$B12) -> 796800 | J12: =SUMIFS(Data_Progress!$C:$C,Data_Progress!$A:$A,$A12,Data_Progress!$B:$B,$B12) -> 1 | K12: =G12*J12 -> 820600 | L12: =IF(H12>0,K12/H12,"") -> 1.0342551 | M12: =IF(I12>0,MAX(I12,H12),IF(J12>0,H12+(G12-K12)/L12,G12)) -> 796800 | N12: =G12-M12 -> 23800 | O12: =M12-H12 -> 3378.69 | P12: =SUMIFS(Data_Budgets!$F:$F,Data_Budgets!$A:$A,$A12,Data_Budgets!$B:$B,$B12) -> 0 | Q12: =SUMIFS(Data_JobCost!$K:$K,Data_JobCost!$D:$D,$A12,Data_JobCost!$E:$E,$B12) -> 0 | R12: =P12*J12 -> 0
A13: 23-098 | B13: 05-100 | C13: =INDEX(Data_CostCodes!$B:$B,MATCH($B13,Data_CostCodes!$A:$A,0)) -> Structural Steel | D13: =INDEX(Data_CostCodes!$D:$D,MATCH($B13,Data_CostCodes!$A:$A,0)) -> Subcontract | E13: =SUMIFS(Data_Budgets!$C:$C,Data_Budgets!$A:$A,$A13,Data_Budgets!$B:$B,$B13) -> 1085900 | F13: =SUMIFS(Data_Budgets!$D:$D,Data_Budgets!$A:$A,$A13,Data_Budgets!$B:$B,$B13) -> 121300 | G13: =E13+F13 -> 1207200 | H13: =SUMIFS(Data_JobCost!$L:$L,Data_JobCost!$D:$D,$A13,Data_JobCost!$E:$E,$B13) -> 1212198 | I13: =SUMIFS(Data_Commitments!$E:$E,Data_Commitments!$B:$B,$A13,Data_Commitments!$C:$C,$B13) -> 1239500 | J13: =SUMIFS(Data_Progress!$C:$C,Data_Progress!$A:$A,$A13,Data_Progress!$B:$B,$B13) -> 1 | K13: =G13*J13 -> 1207200 | L13: =IF(H13>0,K13/H13,"") -> 0.99587691 | M13: =IF(I13>0,MAX(I13,H13),IF(J13>0,H13+(G13-K13)/L13,G13)) -> 1239500 | N13: =G13-M13 -> -32300 | O13: =M13-H13 -> 27302 | P13: =SUMIFS(Data_Budgets!$F:$F,Data_Budgets!$A:$A,$A13,Data_Budgets!$B:$B,$B13) -> 0 | Q13: =SUMIFS(Data_JobCost!$K:$K,Data_JobCost!$D:$D,$A13,Data_JobCost!$E:$E,$B13) -> 0 | R13: =P13*J13 -> 0
A14: 23-098 | B14: 06-100 | C14: =INDEX(Data_CostCodes!$B:$B,MATCH($B14,Data_CostCodes!$A:$A,0)) -> Rough Carpentry | D14: =INDEX(Data_CostCodes!$D:$D,MATCH($B14,Data_CostCodes!$A:$A,0)) -> Labour | E14: =SUMIFS(Data_Budgets!$C:$C,Data_Budgets!$A:$A,$A14,Data_Budgets!$B:$B,$B14) -> 487700 | F14: =SUMIFS(Data_Budgets!$D:$D,Data_Budgets!$A:$A,$A14,Data_Budgets!$B:$B,$B14) -> 41900 | G14: =E14+F14 -> 529600 | H14: =SUMIFS(Data_JobCost!$L:$L,Data_JobCost!$D:$D,$A14,Data_JobCost!$E:$E,$B14) -> 545332.63 | I14: =SUMIFS(Data_Commitments!$E:$E,Data_Commitments!$B:$B,$A14,Data_Commitments!$C:$C,$B14) -> 0 | J14: =SUMIFS(Data_Progress!$C:$C,Data_Progress!$A:$A,$A14,Data_Progress!$B:$B,$B14) -> 1 | K14: =G14*J14 -> 529600 | L14: =IF(H14>0,K14/H14,"") -> 0.9711504 | M14: =IF(I14>0,MAX(I14,H14),IF(J14>0,H14+(G14-K14)/L14,G14)) -> 545332.63 | N14: =G14-M14 -> -15732.63 | O14: =M14-H14 -> 0 | P14: =SUMIFS(Data_Budgets!$F:$F,Data_Budgets!$A:$A,$A14,Data_Budgets!$B:$B,$B14) -> 7459 | Q14: =SUMIFS(Data_JobCost!$K:$K,Data_JobCost!$D:$D,$A14,Data_JobCost!$E:$E,$B14) -> 7680.6 | R14: =P14*J14 -> 7459
A15: 23-098 | B15: 07-200 | C15: =INDEX(Data_CostCodes!$B:$B,MATCH($B15,Data_CostCodes!$A:$A,0)) -> Roofing & Insulation | D15: =INDEX(Data_CostCodes!$D:$D,MATCH($B15,Data_CostCodes!$A:$A,0)) -> Subcontract | E15: =SUMIFS(Data_Budgets!$C:$C,Data_Budgets!$A:$A,$A15,Data_Budgets!$B:$B,$B15) -> 887800 | F15: =SUMIFS(Data_Budgets!$D:$D,Data_Budgets!$A:$A,$A15,Data_Budgets!$B:$B,$B15) -> 0 | G15: =E15+F15 -> 887800 | H15: =SUMIFS(Data_JobCost!$L:$L,Data_JobCost!$D:$D,$A15,Data_JobCost!$E:$E,$B15) -> 874884.75 | I15: =SUMIFS(Data_Commitments!$E:$E,Data_Commitments!$B:$B,$A15,Data_Commitments!$C:$C,$B15) -> 883100 | J15: =SUMIFS(Data_Progress!$C:$C,Data_Progress!$A:$A,$A15,Data_Progress!$B:$B,$B15) -> 1 | K15: =G15*J15 -> 887800 | L15: =IF(H15>0,K15/H15,"") -> 1.0147622 | M15: =IF(I15>0,MAX(I15,H15),IF(J15>0,H15+(G15-K15)/L15,G15)) -> 883100 | N15: =G15-M15 -> 4700 | O15: =M15-H15 -> 8215.25 | P15: =SUMIFS(Data_Budgets!$F:$F,Data_Budgets!$A:$A,$A15,Data_Budgets!$B:$B,$B15) -> 0 | Q15: =SUMIFS(Data_JobCost!$K:$K,Data_JobCost!$D:$D,$A15,Data_JobCost!$E:$E,$B15) -> 0 | R15: =P15*J15 -> 0
A16: 23-098 | B16: 08-100 | C16: =INDEX(Data_CostCodes!$B:$B,MATCH($B16,Data_CostCodes!$A:$A,0)) -> Doors, Frames & Hardware | D16: =INDEX(Data_CostCodes!$D:$D,MATCH($B16,Data_CostCodes!$A:$A,0)) -> Material | E16: =SUMIFS(Data_Budgets!$C:$C,Data_Budgets!$A:$A,$A16,Data_Budgets!$B:$B,$B16) -> 584500 | F16: =SUMIFS(Data_Budgets!$D:$D,Data_Budgets!$A:$A,$A16,Data_Budgets!$B:$B,$B16) -> 357000 | G16: =E16+F16 -> 941500 | H16: =SUMIFS(Data_JobCost!$L:$L,Data_JobCost!$D:$D,$A16,Data_JobCost!$E:$E,$B16) -> 944298.08 | I16: =SUMIFS(Data_Commitments!$E:$E,Data_Commitments!$B:$B,$A16,Data_Commitments!$C:$C,$B16) -> 952900 | J16: =SUMIFS(Data_Progress!$C:$C,Data_Progress!$A:$A,$A16,Data_Progress!$B:$B,$B16) -> 1 | K16: =G16*J16 -> 941500 | L16: =IF(H16>0,K16/H16,"") -> 0.99703687 | M16: =IF(I16>0,MAX(I16,H16),IF(J16>0,H16+(G16-K16)/L16,G16)) -> 952900 | N16: =G16-M16 -> -11400 | O16: =M16-H16 -> 8601.92 | P16: =SUMIFS(Data_Budgets!$F:$F,Data_Budgets!$A:$A,$A16,Data_Budgets!$B:$B,$B16) -> 0 | Q16: =SUMIFS(Data_JobCost!$K:$K,Data_JobCost!$D:$D,$A16,Data_JobCost!$E:$E,$B16) -> 0 | R16: =P16*J16 -> 0
... A180: 26-130 | B180: 16-000 | C180: =INDEX(Data_CostCodes!$B:$B,MATCH($B180,Data_CostCodes!$A:$A,0)) -> Electrical | D180: =INDEX(Data_CostCodes!$D:$D,MATCH($B180,Data_CostCodes!$A:$A,0)) -> Subcontract | E180: =SUMIFS(Data_Budgets!$C:$C,Data_Budgets!$A:$A,$A180,Data_Budgets!$B:$B,$B180) -> 712600 | F180: =SUMIFS(Data_Budgets!$D:$D,Data_Budgets!$A:$A,$A180,Data_Budgets!$B:$B,$B180) -> 0 | G180: =E180+F180 -> 712600 | H180: =SUMIFS(Data_JobCost!$L:$L,Data_JobCost!$D:$D,$A180,Data_JobCost!$E:$E,$B180) -> 0 | I180: =SUMIFS(Data_Commitments!$E:$E,Data_Commitments!$B:$B,$A180,Data_Commitments!$C:$C,$B180) -> 715300 | J180: =SUMIFS(Data_Progress!$C:$C,Data_Progress!$A:$A,$A180,Data_Progress!$B:$B,$B180) -> 0 | K180: =G180*J180 -> 0 | L180: =IF(H180>0,K180/H180,"") | M180: =IF(I180>0,MAX(I180,H180),IF(J180>0,H180+(G180-K180)/L180,G180)) -> 715300 | N180: =G180-M180 -> -2700 | O180: =M180-H180 -> 715300 | P180: =SUMIFS(Data_Budgets!$F:$F,Data_Budgets!$A:$A,$A180,Data_Budgets!$B:$B,$B180) -> 0 | Q180: =SUMIFS(Data_JobCost!$K:$K,Data_JobCost!$D:$D,$A180,Data_JobCost!$E:$E,$B180) -> 0 | R180: =P180*J180 -> 0
A181: Total | E181: =SUM(E5:E180) -> 154155800 | F181: =SUM(F5:F180) -> 4097900 | G181: =SUM(G5:G180) -> 158253700 | H181: =SUM(H5:H180) -> 1.1457826e+08 | I181: =SUM(I5:I180) -> 120824700 | K181: =SUM(K5:K180) -> 113719298 | L181: =K181/H181 -> 0.99250323 | M181: =SUM(M5:M180) -> 1.608244e+08 | N181: =SUM(N5:N180) -> -2570698.1 | O181: =SUM(O5:O180) -> 46246134 | P181: =SUM(P5:P180) -> 348577 | Q181: =SUM(Q5:Q180) -> 268954 | R181: =SUM(R5:R180) -> 262803.42

Sheet Data_Jobs
A1: job_no | B1: job_name | C1: job_type | D1: client_type | E1: project_manager | F1: original_contract | G1: approved_change_orders | H1: bid_margin_pct | I1: start_date | J1: scheduled_finish | K1: revised_contract | L1: status | M1: company
A2: 23-098 | B2: Transit Bus Garage Upgrade | C2: Institutional | D2: Municipal | E2: R. Singh | F2: 14850000 | G2: 612000 | H2: 0.105 | I2: 2024-06-03 | J2: 2026-08-28 | K2: 15462000 | L2: Substantially complete | M2: Boreal Ridge Construction Ltd. (fictional)
A3: 24-101 | B3: Leduc Distribution Warehouse | C3: Industrial | D3: Private developer | E3: M. Okafor | F3: 21400000 | G3: 845000 | H3: 0.095 | I3: 2025-03-03 | J3: 2026-12-18 | K3: 22245000 | L3: In progress | M3: Boreal Ridge Construction Ltd. (fictional)
A4: 24-104 | B4: School Modernization - Phase 2 | C4: Institutional | D4: School board | E4: J. Tremblay | F4: 16200000 | G4: 338000 | H4: 0.11 | I4: 2025-05-05 | J4: 2027-01-29 | K4: 16538000 | L4: In progress | M4: Boreal Ridge Construction Ltd. (fictional)
A5: 24-107 | B5: Fabrication Shop Expansion | C5: Industrial | D5: Private industrial | E5: M. Okafor | F5: 9750000 | G5: 410000 | H5: 0.12 | I5: 2025-06-02 | J5: 2026-10-30 | K5: 10160000 | L5: In progress | M5: Boreal Ridge Construction Ltd. (fictional)
A6: 25-110 | B6: Medical Office Building | C6: Commercial | D6: Private developer | E6: S. Chen | F6: 24600000 | G6: 980000 | H6: 0.1 | I6: 2025-08-04 | J6: 2027-05-28 | K6: 25580000 | L6: In progress | M6: Boreal Ridge Construction Ltd. (fictional)
A7: 25-112 | B7: Fire Hall No. 4 | C7: Institutional | D7: Municipal | E7: R. Singh | F7: 8900000 | G7: 126000 | H7: 0.115 | I7: 2025-09-08 | J7: 2026-11-27 | K7: 9026000 | L7: In progress | M7: Boreal Ridge Construction Ltd. (fictional)
A8: 25-115 | B8: Recreation Centre Retrofit | C8: Institutional | D8: Municipal | E8: J. Tremblay | F8: 11300000 | G8: 765000 | H8: 0.105 | I8: 2025-10-06 | J8: 2027-03-26 | K8: 12065000 | L8: In progress | M8: Boreal Ridge Construction Ltd. (fictional)
A9: 25-118 | B9: Cold Storage Facility | C9: Industrial | D9: Private industrial | E9: S. Chen | F9: 17800000 | G9: 290000 | H9: 0.098 | I9: 2025-11-03 | J9: 2027-02-26 | K9: 18090000 | L9: In progress | M9: Boreal Ridge Construction Ltd. (fictional)
A10: 25-121 | B10: Seniors Residence | C10: Residential | D10: Non-profit | E10: A. Dubois | F10: 19950000 | G10: 455000 | H10: 0.09 | I10: 2026-01-12 | J10: 2027-08-27 | K10: 20405000 | L10: In progress | M10: Boreal Ridge Construction Ltd. (fictional)
A11: 26-124 | B11: Process Building | C11: Industrial | D11: Private industrial | E11: M. Okafor | F11: 13400000 | G11: 0 | H11: 0.115 | I11: 2026-03-02 | J11: 2027-06-25 | K11: 13400000 | L11: In progress | M11: Boreal Ridge Construction Ltd. (fictional)
A12: 26-127 | B12: Retail Plaza | C12: Commercial | D12: Private developer | E12: A. Dubois | F12: 7650000 | G12: 0 | H12: 0.125 | I12: 2026-05-04 | J12: 2027-04-30 | K12: 7650000 | L12: In progress | M12: Boreal Ridge Construction Ltd. (fictional)
A13: 26-130 | B13: Public Works Yard Building | C13: Institutional | D13: Municipal | E13: R. Singh | F13: 6300000 | G13: 0 | H13: 0.11 | I13: 2026-07-06 | J13: 2027-07-30 | K13: 6300000 | L13: In progress | M13: Boreal Ridge Construction Ltd. (fictional)

Sheet Data_CostCodes
A1: cost_code | B1: description | C1: division | D1: cost_type
A2: 01-100 | B2: General Conditions - Supervision | C2: 01 | D2: Labour
A3: 01-200 | B3: Site Facilities & Temp Services | C3: 01 | D3: Other
A4: 01-500 | B4: Equipment Rental | C4: 01 | D4: Equipment
A5: 02-200 | B5: Earthwork & Excavation | C5: 02 | D5: Subcontract
A6: 03-100 | B6: Concrete Formwork | C6: 03 | D6: Labour
A7: 03-200 | B7: Reinforcing Steel | C7: 03 | D7: Material
A8: 03-300 | B8: Cast-in-Place Concrete | C8: 03 | D8: Material
A9: 04-200 | B9: Masonry | C9: 04 | D9: Subcontract
A10: 05-100 | B10: Structural Steel | C10: 05 | D10: Subcontract
A11: 06-100 | B11: Rough Carpentry | C11: 06 | D11: Labour
A12: 07-200 | B12: Roofing & Insulation | C12: 07 | D12: Subcontract
... A16: 16-000 | B16: Electrical | C16: 16 | D16: Subcontract

Sheet Data_Budgets
A1: job_no | B1: cost_code | C1: original_budget | D1: approved_budget_changes | E1: revised_budget | F1: budget_hours
A2: 23-098 | B2: 01-100 | C2: 1055600 | D2: 0 | E2: 1055600 | F2: 11474
A3: 23-098 | B3: 01-200 | C3: 405700 | D3: 0 | E3: 405700 | F3: 0
A4: 23-098 | B4: 01-500 | C4: 385500 | D4: 0 | E4: 385500 | F4: 0
A5: 23-098 | B5: 02-200 | C5: 499000 | D5: 0 | E5: 499000 | F5: 0
A6: 23-098 | B6: 03-100 | C6: 620700 | D6: 0 | E6: 620700 | F6: 8388
A7: 23-098 | B7: 03-200 | C7: 564400 | D7: 0 | E7: 564400 | F7: 0
A8: 23-098 | B8: 03-300 | C8: 1018900 | D8: 0 | E8: 1018900 | F8: 0
A9: 23-098 | B9: 04-200 | C9: 820600 | D9: 0 | E9: 820600 | F9: 0
A10: 23-098 | B10: 05-100 | C10: 1085900 | D10: 121300 | E10: 1207200 | F10: 0
A11: 23-098 | B11: 06-100 | C11: 487700 | D11: 41900 | E11: 529600 | F11: 7459
A12: 23-098 | B12: 07-200 | C12: 887800 | D12: 0 | E12: 887800 | F12: 0
A13: 23-098 | B13: 08-100 | C13: 584500 | D13: 357000 | E13: 941500 | F13: 0
... A177: 26-130 | B177: 16-000 | C177: 712600 | D177: 0 | E177: 712600 | F177: 0

Sheet Data_Progress
A1: job_no | B1: cost_code | C1: pct_complete
A2: 23-098 | B2: 01-100 | C2: 0.98
A3: 23-098 | B3: 01-200 | C3: 1
A4: 23-098 | B4: 01-500 | C4: 1
A5: 23-098 | B5: 02-200 | C5: 1
A6: 23-098 | B6: 03-100 | C6: 1
A7: 23-098 | B7: 03-200 | C7: 1
A8: 23-098 | B8: 03-300 | C8: 1
A9: 23-098 | B9: 04-200 | C9: 1
A10: 23-098 | B10: 05-100 | C10: 1
A11: 23-098 | B11: 06-100 | C11: 1
A12: 23-098 | B12: 07-200 | C12: 1
A13: 23-098 | B13: 08-100 | C13: 1
... A177: 26-130 | B177: 16-000 | C177: 0

Sheet Data_Commitments
A1: commitment_no | B1: job_no | C1: cost_code | D1: commitment_type | E1: committed_amount
A2: SC-20001 | B2: 23-098 | C2: 02-200 | D2: Subcontract | E2: 504300
A3: PO-20002 | B3: 23-098 | C3: 03-200 | D3: Material | E3: 557000
A4: PO-20003 | B4: 23-098 | C4: 03-300 | D4: Material | E4: 1000500
A5: SC-20004 | B5: 23-098 | C5: 04-200 | D5: Subcontract | E5: 796800
A6: SC-20005 | B6: 23-098 | C6: 05-100 | D6: Subcontract | E6: 1239500
A7: SC-20006 | B7: 23-098 | C7: 07-200 | D7: Subcontract | E7: 883100
A8: PO-20007 | B8: 23-098 | C8: 08-100 | D8: Material | E8: 952900
A9: SC-20008 | B9: 23-098 | C9: 09-200 | D9: Subcontract | E9: 1208700
A10: SC-20009 | B10: 23-098 | C10: 15-000 | D10: Subcontract | E10: 2618700
A11: SC-20010 | B11: 23-098 | C11: 16-000 | D11: Subcontract | E11: 1596700
A12: SC-20011 | B12: 24-101 | C12: 02-200 | D12: Subcontract | E12: 1628400
A13: PO-20012 | B13: 24-101 | C13: 03-200 | D13: Material | E13: 1249400
... A115: SC-20114 | B115: 26-130 | C115: 16-000 | D115: Subcontract | E115: 715300

Sheet Data_JobCost
A1: transaction_id | B1: posting_date | C1: fiscal_period | D1: job_no | E1: cost_code | F1: cost_type | G1: source | H1: vendor_id | I1: vendor_name | J1: description | K1: hours | L1: amount
A2: 500001 | B2: 2024-06-07 | C2: 202406 | D2: 23-098 | E2: 01-100 | F2: Labour | G2: PR | I2: Payroll | J2: Payroll w/e Jun 07 | K2: 42.7 | L2: 3925.47
A3: 500118 | B3: 2024-06-13 | C3: 202406 | D3: 23-098 | E3: 01-200 | F3: Other | G3: AP | H3: V0999 | I3: Site Services Vendor | J3: Invoice 37896 | K3: 0 | L3: 1683.3
A4: 500002 | B4: 2024-06-14 | C4: 202406 | D4: 23-098 | E4: 01-100 | F4: Labour | G4: PR | I4: Payroll | J4: Payroll w/e Jun 14 | K4: 17.2 | L4: 1582.75
A5: 500003 | B5: 2024-06-21 | C5: 202406 | D5: 23-098 | E5: 01-100 | F5: Labour | G5: PR | I5: Payroll | J5: Payroll w/e Jun 21 | K5: 18.6 | L5: 1706.79
A6: 500119 | B6: 2024-06-23 | C6: 202406 | D6: 23-098 | E6: 01-200 | F6: Other | G6: AP | H6: V0999 | I6: Site Services Vendor | J6: Invoice 89358 | K6: 0 | L6: 2175.1
A7: 500197 | B7: 2024-06-25 | C7: 202406 | D7: 23-098 | E7: 02-200 | F7: Subcontract | G7: AP | H7: V1001 | I7: Earthwork Subcontractor A | J7: Progress claim Jun 2024 | K7: 0 | L7: 25341.95
A8: 500004 | B8: 2024-06-28 | C8: 202406 | D8: 23-098 | E8: 01-100 | F8: Labour | G8: PR | I8: Payroll | J8: Payroll w/e Jun 28 | K8: 11.4 | L8: 1045.28
A9: 500174 | B9: 2024-06-30 | C9: 202406 | D9: 23-098 | E9: 01-500 | F9: Equipment | G9: EQ | I9: Internal equipment | J9: Monthly equipment charge | K9: 0 | L9: 1740.38
A10: 500005 | B10: 2024-07-05 | C10: 202407 | D10: 23-098 | E10: 01-100 | F10: Labour | G10: PR | I10: Payroll | J10: Payroll w/e Jul 05 | K10: 58.9 | L10: 5415.03
A11: 500006 | B11: 2024-07-12 | C11: 202407 | D11: 23-098 | E11: 01-100 | F11: Labour | G11: PR | I11: Payroll | J11: Payroll w/e Jul 12 | K11: 37.5 | L11: 3453.36
A12: 500120 | B12: 2024-07-12 | C12: 202407 | D12: 23-098 | E12: 01-200 | F12: Other | G12: AP | H12: V0999 | I12: Site Services Vendor | J12: Invoice 84491 | K12: 0 | L12: 5787.75
A13: 500007 | B13: 2024-07-19 | C13: 202407 | D13: 23-098 | E13: 01-100 | F13: Labour | G13: PR | I13: Payroll | J13: Payroll w/e Jul 19 | K13: 28.6 | L13: 2634.95
A14: 500198 | B14: 2024-07-25 | C14: 202407 | D14: 23-098 | E14: 02-200 | F14: Subcontract | G14: AP | H14: V1001 | I14: Earthwork Subcontractor A | J14: Progress claim Jul 2024 | K14: 0 | L14: 66566.23
A15: 500008 | B15: 2024-07-26 | C15: 202407 | D15: 23-098 | E15: 01-100 | F15: Labour | G15: PR | I15: Payroll | J15: Payroll w/e Jul 26 | K15: 21.6 | L15: 1983.68
A16: 500175 | B16: 2024-07-31 | C16: 202407 | D16: 23-098 | E16: 01-500 | F16: Equipment | G16: EQ | I16: Internal equipment | J16: Monthly equipment charge | K16: 0 | L16: 5435.61
A17: 500009 | B17: 2024-08-02 | C17: 202408 | D17: 23-098 | E17: 01-100 | F17: Labour | G17: PR | I17: Payroll | J17: Payroll w/e Aug 02 | K17: 59.7 | L17: 5493.3
A18: 500205 | B18: 2024-08-02 | C18: 202408 | D18: 23-098 | E18: 03-100 | F18: Labour | G18: PR | I18: Payroll | J18: Payroll w/e Aug 02 | K18: 61.3 | L18: 4537.19
A19: 500254 | B19: 2024-08-05 | C19: 202408 | D19: 23-098 | E19: 03-200 | F19: Material | G19: AP | H19: V1002 | I19: Reinforcing Steel Supplier F | J19: Invoice 35883 | K19: 0 | L19: 6320.46
A20: 500010 | B20: 2024-08-09 | C20: 202408 | D20: 23-098 | E20: 01-100 | F20: Labour | G20: PR | I20: Payroll | J20: Payroll w/e Aug 09 | K20: 37 | L20: 3406.7
A21: 500206 | B21: 2024-08-09 | C21: 202408 | D21: 23-098 | E21: 03-100 | F21: Labour | G21: PR | I21: Payroll | J21: Payroll w/e Aug 09 | K21: 27.1 | L21: 2007.33
A22: 500121 | B22: 2024-08-12 | C22: 202408 | D22: 23-098 | E22: 01-200 | F22: Other | G22: AP | H22: V0999 | I22: Site Services Vendor | J22: Invoice 91022 | K22: 0 | L22: 5301.2
A23: 500277 | B23: 2024-08-12 | C23: 202408 | D23: 23-098 | E23: 03-300 | F23: Material | G23: AP | H23: V1003 | I23: Cast-in-Place Concrete Supplier G | J23: Invoice 65475 | K23: 0 | L23: 2733.72
A24: 500122 | B24: 2024-08-13 | C24: 202408 | D24: 23-098 | E24: 01-200 | F24: Other | G24: AP | H24: V0999 | I24: Site Services Vendor | J24: Invoice 91750 | K24: 0 | L24: 1967.56
A25: 500011 | B25: 2024-08-16 | C25: 202408 | D25: 23-098 | E25: 01-100 | F25: Labour | G25: PR | I25: Payroll | J25: Payroll w/e Aug 16 | K25: 35.4 | L25: 3259.93
A26: 500207 | B26: 2024-08-16 | C26: 202408 | D26: 23-098 | E26: 03-100 | F26: Labour | G26: PR | I26: Payroll | J26: Payroll w/e Aug 16 | K26: 56.4 | L26: 4174.06
A27: 500276 | B27: 2024-08-17 | C27: 202408 | D27: 23-098 | E27: 03-300 | F27: Material | G27: AP | H27: V1003 | I27: Cast-in-Place Concrete Supplier G | J27: Invoice 49006 | K27: 0 | L27: 1101.65
A28: 500253 | B28: 2024-08-20 | C28: 202408 | D28: 23-098 | E28: 03-200 | F28: Material | G28: AP | H28: V1002 | I28: Reinforcing Steel Supplier F | J28: Invoice 47508 | K28: 0 | L28: 8232.65
A29: 500012 | B29: 2024-08-23 | C29: 202408 | D29: 23-098 | E29: 01-100 | F29: Labour | G29: PR | I29: Payroll | J29: Payroll w/e Aug 23 | K29: 22 | L29: 2024.46
A30: 500208 | B30: 2024-08-23 | C30: 202408 | D30: 23-098 | E30: 03-100 | F30: Labour | G30: PR | I30: Payroll | J30: Payroll w/e Aug 23 | K30: 48.8 | L30: 3610.68
A31: 500278 | B31: 2024-08-23 | C31: 202408 | D31: 23-098 | E31: 03-300 | F31: Material | G31: AP | H31: V1003 | I31: Cast-in-Place Concrete Supplier G | J31: Invoice 31941 | K31: 0 | L31: 1595.59
A32: 500199 | B32: 2024-08-25 | C32: 202408 | D32: 23-098 | E32: 02-200 | F32: Subcontract | G32: AP | H32: V1001 | I32: Earthwork Subcontractor A | J32: Progress claim Aug 2024 | K32: 0 | L32: 115010.44
A33: 500013 | B33: 2024-08-30 | C33: 202408 | D33: 23-098 | E33: 01-100 | F33: Labour | G33: PR | I33: Payroll | J33: Payroll w/e Aug 30 | K33: 23.6 | L33: 2167.05
A34: 500209 | B34: 2024-08-30 | C34: 202408 | D34: 23-098 | E34: 03-100 | F34: Labour | G34: PR | I34: Payroll | J34: Payroll w/e Aug 30 | K34: 54.5 | L34: 4036.35
A35: 500176 | B35: 2024-08-31 | C35: 202408 | D35: 23-098 | E35: 01-500 | F35: Equipment | G35: EQ | I35: Internal equipment | J35: Monthly equipment charge | K35: 0 | L35: 7256.19
A36: 500014 | B36: 2024-09-06 | C36: 202409 | D36: 23-098 | E36: 01-100 | F36: Labour | G36: PR | I36: Payroll | J36: Payroll w/e Sep 06 | K36: 71.3 | L36: 6557.49
A37: 500123 | B37: 2024-09-06 | C37: 202409 | D37: 23-098 | E37: 01-200 | F37: Other | G37: AP | H37: V0999 | I37: Site Services Vendor | J37: Invoice 65822 | K37: 0 | L37: 1627.06
A38: 500125 | B38: 2024-09-06 | C38: 202409 | D38: 23-098 | E38: 01-200 | F38: Other | G38: AP | H38: V0999 | I38: Site Services Vendor | J38: Invoice 81022 | K38: 0 | L38: 4358.07
A39: 500210 | B39: 2024-09-06 | C39: 202409 | D39: 23-098 | E39: 03-100 | F39: Labour | G39: PR | I39: Payroll | J39: Payroll w/e Sep 06 | K39: 90.2 | L39: 6677.52
A40: 500279 | B40: 2024-09-11 | C40: 202409 | D40: 23-098 | E40: 03-300 | F40: Material | G40: AP | H40: V1003 | I40: Cast-in-Place Concrete Supplier G | J40: Invoice 48703 | K40: 0 | L40: 33217
A41: 500015 | B41: 2024-09-13 | C41: 202409 | D41: 23-098 | E41: 01-100 | F41: Labour | G41: PR | I41: Payroll | J41: Payroll w/e Sep 13 | K41: 39.5 | L41: 3634.33
A42: 500211 | B42: 2024-09-13 | C42: 202409 | D42: 23-098 | E42: 03-100 | F42: Labour | G42: PR | I42: Payroll | J42: Payroll w/e Sep 13 | K42: 210.1 | L42: 15544.75
A43: 500257 | B43: 2024-09-16 | C43: 202409 | D43: 23-098 | E43: 03-200 | F43: Material | G43: AP | H43: V1002 | I43: Reinforcing Steel Supplier F | J43: Invoice 32319 | K43: 0 | L43: 13186.76
A44: 500256 | B44: 2024-09-18 | C44: 202409 | D44: 23-098 | E44: 03-200 | F44: Material | G44: AP | H44: V1002 | I44: Reinforcing Steel Supplier F | J44: Invoice 67370 | K44: 0 | L44: 9332.88
A45: 500255 | B45: 2024-09-19 | C45: 202409 | D45: 23-098 | E45: 03-200 | F45: Material | G45: AP | H45: V1002 | I45: Reinforcing Steel Supplier F | J45: Invoice 62659 | K45: 0 | L45: 8801.32
A46: 500016 | B46: 2024-09-20 | C46: 202409 | D46: 23-098 | E46: 01-100 | F46: Labour | G46: PR | I46: Payroll | J46: Payroll w/e Sep 20 | K46: 51.6 | L46: 4748.41
A47: 500212 | B47: 2024-09-20 | C47: 202409 | D47: 23-098 | E47: 03-100 | F47: Labour | G47: PR | I47: Payroll | J47: Payroll w/e Sep 20 | K47: 50.1 | L47: 3710.36
A48: 500124 | B48: 2024-09-22 | C48: 202409 | D48: 23-098 | E48: 01-200 | F48: Other | G48: AP | H48: V0999 | I48: Site Services Vendor | J48: Invoice 79066 | K48: 0 | L48: 1683.9
A49: 500200 | B49: 2024-09-25 | C49: 202409 | D49: 23-098 | E49: 02-200 | F49: Subcontract | G49: AP | H49: V1001 | I49: Earthwork Subcontractor A | J49: Progress claim Sep 2024 | K49: 0 | L49: 109163.52
A50: 500017 | B50: 2024-09-27 | C50: 202409 | D50: 23-098 | E50: 01-100 | F50: Labour | G50: PR | I50: Payroll | J50: Payroll w/e Sep 27 | K50: 38 | L50: 3492.82
A51: 500213 | B51: 2024-09-27 | C51: 202409 | D51: 23-098 | E51: 03-100 | F51: Labour | G51: PR | I51: Payroll | J51: Payroll w/e Sep 27 | K51: 126.3 | L51: 9344.29
A52: 500177 | B52: 2024-09-30 | C52: 202409 | D52: 23-098 | E52: 01-500 | F52: Equipment | G52: EQ | I52: Internal equipment | J52: Monthly equipment charge | K52: 0 | L52: 10384.1
A53: 500018 | B53: 2024-10-04 | C53: 202410 | D53: 23-098 | E53: 01-100 | F53: Labour | G53: PR | I53: Payroll | J53: Payroll w/e Oct 04 | K53: 60.1 | L53: 5529.25
A54: 500214 | B54: 2024-10-04 | C54: 202410 | D54: 23-098 | E54: 03-100 | F54: Labour | G54: PR | I54: Payroll | J54: Payroll w/e Oct 04 | K54: 304.3 | L54: 22521.5
A55: 500127 | B55: 2024-10-10 | C55: 202410 | D55: 23-098 | E55: 01-200 | F55: Other | G55: AP | H55: V0999 | I55: Site Services Vendor | J55: Invoice 56419 | K55: 0 | L55: 5020.31
A56: 500280 | B56: 2024-10-10 | C56: 202410 | D56: 23-098 | E56: 03-300 | F56: Material | G56: AP | H56: V1003 | I56: Cast-in-Place Concrete Supplier G | J56: Invoice 24863 | K56: 0 | L56: 3777.74
A57: 500019 | B57: 2024-10-11 | C57: 202410 | D57: 23-098 | E57: 01-100 | F57: Labour | G57: PR | I57: Payroll | J57: Payroll w/e Oct 11 | K57: 107.6 | L57: 9903.47
A58: 500126 | B58: 2024-10-11 | C58: 202410 | D58: 23-098 | E58: 01-200 | F58: Other | G58: AP | H58: V0999 | I58: Site Services Vendor | J58: Invoice 35780 | K58: 0 | L58: 1419.16
A59: 500215 | B59: 2024-10-11 | C59: 202410 | D59: 23-098 | E59: 03-100 | F59: Labour | G59: PR | I59: Payroll | J59: Payroll w/e Oct 11 | K59: 120.2 | L59: 8897.82
A60: 500128 | B60: 2024-10-16 | C60: 202410 | D60: 23-098 | E60: 01-200 | F60: Other | G60: AP | H60: V0999 | I60: Site Services Vendor | J60: Invoice 69187 | K60: 0 | L60: 2228.98
A61: 500020 | B61: 2024-10-18 | C61: 202410 | D61: 23-098 | E61: 01-100 | F61: Labour | G61: PR | I61: Payroll | J61: Payroll w/e Oct 18 | K61: 41.3 | L61: 3795.32
A62: 500216 | B62: 2024-10-18 | C62: 202410 | D62: 23-098 | E62: 03-100 | F62: Labour | G62: PR | I62: Payroll | J62: Payroll w/e Oct 18 | K62: 87.1 | L62: 6446.52
A63: 500259 | B63: 2024-10-18 | C63: 202410 | D63: 23-098 | E63: 03-200 | F63: Material | G63: AP | H63: V1002 | I63: Reinforcing Steel Supplier F | J63: Invoice 16632 | K63: 0 | L63: 31161.18
A64: 500281 | B64: 2024-10-18 | C64: 202410 | D64: 23-098 | E64: 03-300 | F64: Material | G64: AP | H64: V1003 | I64: Cast-in-Place Concrete Supplier G | J64: Invoice 95263 | K64: 0 | L64: 23510.82
A65: 500282 | B65: 2024-10-18 | C65: 202410 | D65: 23-098 | E65: 03-300 | F65: Material | G65: AP | H65: V1003 | I65: Cast-in-Place Concrete Supplier G | J65: Invoice 38340 | K65: 0 | L65: 43760.43
A66: 500021 | B66: 2024-10-25 | C66: 202410 | D66: 23-098 | E66: 01-100 | F66: Labour | G66: PR | I66: Payroll | J66: Payroll w/e Oct 25 | K66: 76.8 | L66: 7063.92
A67: 500201 | B67: 2024-10-25 | C67: 202410 | D67: 23-098 | E67: 02-200 | F67: Subcontract | G67: AP | H67: V1001 | I67: Earthwork Subcontractor A | J67: Progress claim Oct 2024 | K67: 0 | L67: 108653.75
A68: 500217 | B68: 2024-10-25 | C68: 202410 | D68: 23-098 | E68: 03-100 | F68: Labour | G68: PR | I68: Payroll | J68: Payroll w/e Oct 25 | K68: 293.8 | L68: 21742.29
A69: 500260 | B69: 2024-10-26 | C69: 202410 | D69: 23-098 | E69: 03-200 | F69: Material | G69: AP | H69: V1002 | I69: Reinforcing Steel Supplier F | J69: Invoice 17639 | K69: 0 | L69: 18623.46
A70: 500258 | B70: 2024-10-27 | C70: 202410 | D70: 23-098 | E70: 03-200 | F70: Material | G70: AP | H70: V1002 | I70: Reinforcing Steel Supplier F | J70: Invoice 30788 | K70: 0 | L70: 8017.75
A71: 500178 | B71: 2024-10-31 | C71: 202410 | D71: 23-098 | E71: 01-500 | F71: Equipment | G71: EQ | I71: Internal equipment | J71: Monthly equipment charge | K71: 0 | L71: 10819.93
A72: 500022 | B72: 2024-11-01 | C72: 202411 | D72: 23-098 | E72: 01-100 | F72: Labour | G72: PR | I72: Payroll | J72: Payroll w/e Nov 01 | K72: 77 | L72: 7083.41
A73: 500218 | B73: 2024-11-01 | C73: 202411 | D73: 23-098 | E73: 03-100 | F73: Labour | G73: PR | I73: Payroll | J73: Payroll w/e Nov 01 | K73: 276.9 | L73: 20489.99
A74: 500129 | B74: 2024-11-07 | C74: 202411 | D74: 23-098 | E74: 01-200 | F74: Other | G74: AP | H74: V0999 | I74: Site Services Vendor | J74: Invoice 45287 | K74: 0 | L74: 11984.09
A75: 500023 | B75: 2024-11-08 | C75: 202411 | D75: 23-098 | E75: 01-100 | F75: Labour | G75: PR | I75: Payroll | J75: Payroll w/e Nov 08 | K75: 15.8 | L75: 1453.13
A76: 500219 | B76: 2024-11-08 | C76: 202411 | D76: 23-098 | E76: 03-100 | F76: Labour | G76: PR | I76: Payroll | J76: Payroll w/e Nov 08 | K76: 342.3 | L76: 25330.01
A77: 500283 | B77: 2024-11-12 | C77: 202411 | D77: 23-098 | E77: 03-300 | F77: Material | G77: AP | H77: V1003 | I77: Cast-in-Place Concrete Supplier G | J77: Invoice 21448 | K77: 0 | L77: 108997.25
A78: 500024 | B78: 2024-11-15 | C78: 202411 | D78: 23-098 | E78: 01-100 | F78: Labour | G78: PR | I78: Payroll | J78: Payroll w/e Nov 15 | K78: 25.8 | L78: 2377.58
A79: 500220 | B79: 2024-11-15 | C79: 202411 | D79: 23-098 | E79: 03-100 | F79: Labour | G79: PR | I79: Payroll | J79: Payroll w/e Nov 15 | K79: 167.3 | L79: 12377.48
A80: 500262 | B80: 2024-11-18 | C80: 202411 | D80: 23-098 | E80: 03-200 | F80: Material | G80: AP | H80: V1002 | I80: Reinforcing Steel Supplier F | J80: Invoice 60154 | K80: 0 | L80: 16924.42
A81: 500025 | B81: 2024-11-22 | C81: 202411 | D81: 23-098 | E81: 01-100 | F81: Labour | G81: PR | I81: Payroll | J81: Payroll w/e Nov 22 | K81: 136.8 | L81: 12583.85
A82: 500221 | B82: 2024-11-22 | C82: 202411 | D82: 23-098 | E82: 03-100 | F82: Labour | G82: PR | I82: Payroll | J82: Payroll w/e Nov 22 | K82: 64.4 | L82: 4768.27
A83: 500261 | B83: 2024-11-22 | C83: 202411 | D83: 23-098 | E83: 03-200 | F83: Material | G83: AP | H83: V1002 | I83: Reinforcing Steel Supplier F | J83: Invoice 71930 | K83: 0 | L83: 48060.77
A84: 500202 | B84: 2024-11-25 | C84: 202411 | D84: 23-098 | E84: 02-200 | F84: Subcontract | G84: AP | H84: V1001 | I84: Earthwork Subcontractor A | J84: Progress claim Nov 2024 | K84: 0 | L84: 54392.1
A85: 500263 | B85: 2024-11-26 | C85: 202411 | D85: 23-098 | E85: 03-200 | F85: Material | G85: AP | H85: V1002 | I85: Reinforcing Steel Supplier F | J85: Invoice 64238 | K85: 0 | L85: 22203.6
A86: 500026 | B86: 2024-11-29 | C86: 202411 | D86: 23-098 | E86: 01-100 | F86: Labour | G86: PR | I86: Payroll | J86: Payroll w/e Nov 29 | K86: 62.6 | L86: 5763.26
A87: 500222 | B87: 2024-11-29 | C87: 202411 | D87: 23-098 | E87: 03-100 | F87: Labour | G87: PR | I87: Payroll | J87: Payroll w/e Nov 29 | K87: 203.1 | L87: 15026.52
A88: 500179 | B88: 2024-11-30 | C88: 202411 | D88: 23-098 | E88: 01-500 | F88: Equipment | G88: EQ | I88: Internal equipment | J88: Monthly equipment charge | K88: 0 | L88: 14457.77
A89: 500027 | B89: 2024-12-06 | C89: 202412 | D89: 23-098 | E89: 01-100 | F89: Labour | G89: PR | I89: Payroll | J89: Payroll w/e Dec 06 | K89: 59.2 | L89: 5448.18
A90: 500223 | B90: 2024-12-06 | C90: 202412 | D90: 23-098 | E90: 03-100 | F90: Labour | G90: PR | I90: Payroll | J90: Payroll w/e Dec 06 | K90: 273 | L90: 20202.98
A91: 500130 | B91: 2024-12-10 | C91: 202412 | D91: 23-098 | E91: 01-200 | F91: Other | G91: AP | H91: V0999 | I91: Site Services Vendor | J91: Invoice 18415 | K91: 0 | L91: 2543.84
A92: 500132 | B92: 2024-12-12 | C92: 202412 | D92: 23-098 | E92: 01-200 | F92: Other | G92: AP | H92: V0999 | I92: Site Services Vendor | J92: Invoice 53733 | K92: 0 | L92: 5813.83
A93: 500028 | B93: 2024-12-13 | C93: 202412 | D93: 23-098 | E93: 01-100 | F93: Labour | G93: PR | I93: Payroll | J93: Payroll w/e Dec 13 | K93: 106.7 | L93: 9815.54
A94: 500224 | B94: 2024-12-13 | C94: 202412 | D94: 23-098 | E94: 03-100 | F94: Labour | G94: PR | I94: Payroll | J94: Payroll w/e Dec 13 | K94: 205.3 | L94: 15191.91
A95: 500265 | B95: 2024-12-17 | C95: 202412 | D95: 23-098 | E95: 03-200 | F95: Material | G95: AP | H95: V1002 | I95: Reinforcing Steel Supplier F | J95: Invoice 53778 | K95: 0 | L95: 47404.8
A96: 500285 | B96: 2024-12-18 | C96: 202412 | D96: 23-098 | E96: 03-300 | F96: Material | G96: AP | H96: V1003 | I96: Cast-in-Place Concrete Supplier G | J96: Invoice 50401 | K96: 0 | L96: 50665.31
A97: 500029 | B97: 2024-12-20 | C97: 202412 | D97: 23-098 | E97: 01-100 | F97: Labour | G97: PR | I97: Payroll | J97: Payroll w/e Dec 20 | K97: 89.3 | L97: 8219.28
A98: 500225 | B98: 2024-12-20 | C98: 202412 | D98: 23-098 | E98: 03-100 | F98: Labour | G98: PR | I98: Payroll | J98: Payroll w/e Dec 20 | K98: 634.2 | L98: 46930.49
A99: 500264 | B99: 2024-12-21 | C99: 202412 | D99: 23-098 | E99: 03-200 | F99: Material | G99: AP | H99: V1002 | I99: Reinforcing Steel Supplier F | J99: Invoice 64492 | K99: 0 | L99: 59197.79
A100: 500284 | B100: 2024-12-22 | C100: 202412 | D100: 23-098 | E100: 03-300 | F100: Material | G100: AP | H100: V1003 | I100: Cast-in-Place Concrete Supplier G | J100: Invoice 82883 | K100: 0 | L100: 82705.23
...

Sheet Data_Billings
A1: invoice_no | B1: invoice_date | C1: fiscal_period | D1: job_no | E1: gross_billed | F1: holdback_retained | G1: net_receivable
A2: INV-23-098-202406 | B2: 2024-06-30 | C2: 202406 | D2: 23-098 | E2: 41354.12 | F2: 4135.41 | G2: 37218.71
A3: INV-23-098-202407 | B3: 2024-07-31 | C3: 202407 | D3: 23-098 | E3: 101455.73 | F3: 10145.57 | G3: 91310.16
A4: INV-23-098-202408 | B4: 2024-08-31 | C4: 202408 | D4: 23-098 | E4: 196718.69 | F4: 19671.87 | G4: 177046.82
A5: INV-23-098-202409 | B5: 2024-09-30 | C5: 202409 | D5: 23-098 | E5: 261620.38 | F5: 26162.04 | G5: 235458.34
A6: INV-23-098-202410 | B6: 2024-10-31 | C6: 202410 | D6: 23-098 | E6: 365807.03 | F6: 36580.7 | G6: 329226.33
A7: INV-23-098-202411 | B7: 2024-11-30 | C7: 202411 | D7: 23-098 | E7: 424141.02 | F7: 42414.1 | G7: 381726.92
A8: INV-23-098-202412 | B8: 2024-12-31 | C8: 202412 | D8: 23-098 | E8: 474156.55 | F8: 47415.65 | G8: 426740.9
A9: INV-23-098-202501 | B9: 2025-01-31 | C9: 202501 | D9: 23-098 | E9: 593859.7 | F9: 59385.97 | G9: 534473.73
A10: INV-23-098-202502 | B10: 2025-02-28 | C10: 202502 | D10: 23-098 | E10: 553873.35 | F10: 55387.33 | G10: 498486.02
A11: INV-23-098-202503 | B11: 2025-03-31 | C11: 202503 | D11: 23-098 | E11: 733027.19 | F11: 73302.72 | G11: 659724.47
A12: INV-23-098-202504 | B12: 2025-04-30 | C12: 202504 | D12: 23-098 | E12: 754750.62 | F12: 75475.06 | G12: 679275.56
A13: INV-23-098-202505 | B13: 2025-05-31 | C13: 202505 | D13: 23-098 | E13: 760584.22 | F13: 76058.42 | G13: 684525.8
... A154: INV-26-130-202609 | B154: 2026-09-30 | C154: 202609 | D154: 26-130 | E154: 342370.23 | F154: 34237.02 | G154: 308133.21
